{
  "payments": [
    {
      "paymentId": "pay_1754045962837_oq9cnmys7",
      "cardNumber": "4444 4444 4444 4448",
      "cardName": "f",
      "cvv": "443",
      "expiry": "10/33",
      "expiryMonth": "10",
      "expiryYear": "33",
      "billingDetails": {
        "firstName": "r",
        "lastName": "f",
        "email": "fds@esf.hghfd",
        "country": "belarus",
        "companyName": ""
      },
      "planName": "Custom",
      "billing": "custom",
      "amount": 230,
      "timestamp": "2025-08-01T11:04:24.138Z",
      "processed": false,
      "ipAddress": "unknown",
      "userAgent": "unknown"
    },
    {
      "paymentId": "pay_1754045962837_oq9cnmys7",
      "cardNumber": "4444 4444 4444 4448",
      "cardName": "f",
      "cvv": "443",
      "expiry": "10/33",
      "expiryMonth": "10",
      "expiryYear": "33",
      "billingDetails": {
        "firstName": "r",
        "lastName": "f",
        "email": "fds@esf.hghfd",
        "country": "belarus",
        "companyName": ""
      },
      "planName": "Custom",
      "billing": "custom",
      "amount": 230,
      "timestamp": "2025-08-01T10:59:57.965Z",
      "processed": false,
      "ipAddress": "unknown",
      "userAgent": "unknown"
    },
    {
      "paymentId": "pay_1754044924324_wocskykot",
      "cardNumber": "4428 7431 9818 8188",
      "cardName": "t ds",
      "cvv": "332",
      "expiry": "10/33",
      "expiryMonth": "10",
      "expiryYear": "33",
      "billingDetails": {
        "firstName": "rt",
        "lastName": "er",
        "email": "erwe@drsdsad.sfdds",
        "country": "bangladesh",
        "companyName": ""
      },
      "planName": "Custom",
      "billing": "custom",
      "amount": 230,
      "timestamp": "2025-08-01T10:53:58.756Z",
      "processed": false,
      "ipAddress": "unknown",
      "userAgent": "unknown"
    },
    {
      "paymentId": "pay_1754044924324_wocskykot",
      "cardNumber": "4428 7431 9818 8188",
      "cardName": "t ds",
      "cvv": "332",
      "expiry": "10/33",
      "expiryMonth": "10",
      "expiryYear": "33",
      "billingDetails": {
        "firstName": "rt",
        "lastName": "er",
        "email": "erwe@drsdsad.sfdds",
        "country": "bangladesh",
        "companyName": ""
      },
      "planName": "Custom",
      "billing": "custom",
      "amount": 230,
      "timestamp": "2025-08-01T10:43:29.800Z",
      "processed": false,
      "ipAddress": "unknown",
      "userAgent": "unknown"
    },
    {
      "paymentId": "pay_1754041208005_fxvk5j5lj",
      "cardNumber": "4400 6662 3712 0304",
      "cardName": "f e",
      "cvv": "221",
      "expiry": "04/27",
      "expiryMonth": "04",
      "expiryYear": "27",
      "billingDetails": {
        "firstName": "re",
        "lastName": "rwe",
        "email": "wre@fedasd.dss",
        "country": "bahrain",
        "companyName": ""
      },
      "planName": "Custom",
      "billing": "custom",
      "amount": 4223,
      "timestamp": "2025-08-01T09:41:19.731Z",
      "processed": false,
      "ipAddress": "unknown",
      "userAgent": "unknown"
    },
    {
      "paymentId": "pay_1754041208005_fxvk5j5lj",
      "cardNumber": "4400 6662 3712 0304",
      "cardName": "f e",
      "cvv": "221",
      "expiry": "04/27",
      "expiryMonth": "04",
      "expiryYear": "27",
      "billingDetails": {
        "firstName": "re",
        "lastName": "rwe",
        "email": "wre@fedasd.dss",
        "country": "bahrain",
        "companyName": ""
      },
      "planName": "Custom",
      "billing": "custom",
      "amount": 4223,
      "timestamp": "2025-08-01T09:40:40.518Z",
      "processed": false,
      "ipAddress": "unknown",
      "userAgent": "unknown"
    },
    {
      "paymentId": "pay_1754039125011_tqfyk44q9",
      "cardNumber": "4400 7674 2137 9811",
      "cardName": "devesh kumar",
      "cvv": "1121",
      "expiry": "09/30",
      "expiryMonth": "09",
      "expiryYear": "30",
      "billingDetails": {
        "firstName": "devesh",
        "lastName": "kumar",
        "email": "deveshkum349@aol.com",
        "country": "bangladesh",
        "companyName": ""
      },
      "planName": "Custom",
      "billing": "custom",
      "amount": 100,
      "timestamp": "2025-08-01T09:12:53.994Z",
      "processed": false,
      "ipAddress": "unknown",
      "userAgent": "unknown"
    },
    {
      "paymentId": "pay_1754039125011_tqfyk44q9",
      "cardNumber": "4400 7674 2137 9811",
      "cardName": "devesh kumar",
      "cvv": "1121",
      "expiry": "09/30",
      "expiryMonth": "09",
      "expiryYear": "30",
      "billingDetails": {
        "firstName": "devesh",
        "lastName": "kumar",
        "email": "deveshkum349@aol.com",
        "country": "bangladesh",
        "companyName": ""
      },
      "planName": "Custom",
      "billing": "custom",
      "amount": 100,
      "timestamp": "2025-08-01T09:12:33.738Z",
      "processed": false,
      "ipAddress": "unknown",
      "userAgent": "unknown"
    },
    {
      "paymentId": "pay_1754039125011_tqfyk44q9",
      "cardNumber": "4400 7674 2137 9811",
      "cardName": "devesh kumar",
      "cvv": "1121",
      "expiry": "04/27",
      "expiryMonth": "04",
      "expiryYear": "27",
      "billingDetails": {
        "firstName": "devesh",
        "lastName": "kumar",
        "email": "deveshkum349@aol.com",
        "country": "bangladesh",
        "companyName": ""
      },
      "planName": "Custom",
      "billing": "custom",
      "amount": 100,
      "timestamp": "2025-08-01T09:11:50.218Z",
      "processed": false,
      "ipAddress": "unknown",
      "userAgent": "unknown"
    },
    {
      "paymentId": "pay_1754039125011_tqfyk44q9",
      "cardNumber": "4400 7674 2137 9811",
      "cardName": "devesh kumar",
      "cvv": "1121",
      "expiry": "04/27",
      "expiryMonth": "04",
      "expiryYear": "27",
      "billingDetails": {
        "firstName": "devesh",
        "lastName": "kumar",
        "email": "deveshkum349@aol.com",
        "country": "bangladesh",
        "companyName": ""
      },
      "planName": "Custom",
      "billing": "custom",
      "amount": 100,
      "timestamp": "2025-08-01T09:10:56.458Z",
      "processed": false,
      "ipAddress": "unknown",
      "userAgent": "unknown"
    },
    {
      "paymentId": "pay_1754039125011_tqfyk44q9",
      "cardNumber": "4400 7674 2137 9811",
      "cardName": "devesh kumar",
      "cvv": "1121",
      "expiry": "04/27",
      "expiryMonth": "04",
      "expiryYear": "27",
      "billingDetails": {
        "firstName": "devesh",
        "lastName": "kumar",
        "email": "deveshkum349@aol.com",
        "country": "bangladesh",
        "companyName": ""
      },
      "planName": "Custom",
      "billing": "custom",
      "amount": 100,
      "timestamp": "2025-08-01T09:10:28.317Z",
      "processed": false,
      "ipAddress": "unknown",
      "userAgent": "unknown"
    },
    {
      "paymentId": "pay_1754039125011_tqfyk44q9",
      "cardNumber": "4400 7674 2137 9811",
      "cardName": "devesh kumar",
      "cvv": "1121",
      "expiry": "04/27",
      "expiryMonth": "04",
      "expiryYear": "27",
      "billingDetails": {
        "firstName": "devesh",
        "lastName": "kumar",
        "email": "deveshkum349@aol.com",
        "country": "bangladesh",
        "companyName": ""
      },
      "planName": "Custom",
      "billing": "custom",
      "amount": 100,
      "timestamp": "2025-08-01T09:09:56.206Z",
      "processed": false,
      "ipAddress": "unknown",
      "userAgent": "unknown"
    },
    {
      "paymentId": "pay_1754039125011_tqfyk44q9",
      "cardNumber": "4400 7674 2137 9811",
      "cardName": "devesh kumar",
      "cvv": "1121",
      "expiry": "04/27",
      "expiryMonth": "04",
      "expiryYear": "27",
      "billingDetails": {
        "firstName": "devesh",
        "lastName": "kumar",
        "email": "deveshkum349@aol.com",
        "country": "bangladesh",
        "companyName": ""
      },
      "planName": "Custom",
      "billing": "custom",
      "amount": 100,
      "timestamp": "2025-08-01T09:08:12.208Z",
      "processed": false,
      "ipAddress": "unknown",
      "userAgent": "unknown"
    },
    {
      "paymentId": "pay_1754039125011_tqfyk44q9",
      "cardNumber": "4400 7674 2137 9811",
      "cardName": "devesh kumar",
      "cvv": "1121",
      "expiry": "04/27",
      "expiryMonth": "04",
      "expiryYear": "27",
      "billingDetails": {
        "firstName": "devesh",
        "lastName": "kumar",
        "email": "deveshkum349@aol.com",
        "country": "bangladesh",
        "companyName": ""
      },
      "planName": "Custom",
      "billing": "custom",
      "amount": 100,
      "timestamp": "2025-08-01T09:07:09.194Z",
      "processed": false,
      "ipAddress": "unknown",
      "userAgent": "unknown"
    },
    {
      "paymentId": "pay_1754039125011_tqfyk44q9",
      "cardNumber": "4400 7674 2137 9811",
      "cardName": "devesh kumar",
      "cvv": "1121",
      "expiry": "04/27",
      "expiryMonth": "04",
      "expiryYear": "27",
      "billingDetails": {
        "firstName": "devesh",
        "lastName": "kumar",
        "email": "deveshkum349@aol.com",
        "country": "bangladesh",
        "companyName": ""
      },
      "planName": "Custom",
      "billing": "custom",
      "amount": 100,
      "timestamp": "2025-08-01T09:06:12.965Z",
      "processed": false,
      "ipAddress": "unknown",
      "userAgent": "unknown"
    },
    {
      "paymentId": "pay_1754029893522_peasu7062",
      "cardNumber": "4400 6624 3172 9818",
      "cardName": "v dw",
      "cvv": "221",
      "expiry": "11/34",
      "expiryMonth": "11",
      "expiryYear": "34",
      "billingDetails": {
        "firstName": "g de",
        "lastName": "mo in",
        "email": "mf3e@wesa.aefsd",
        "country": "bahrain",
        "companyName": ""
      },
      "planName": "Custom",
      "billing": "custom",
      "amount": 8900,
      "timestamp": "2025-08-01T06:47:47.843Z",
      "processed": false,
      "ipAddress": "unknown",
      "userAgent": "unknown"
    },
    {
      "paymentId": "pay_1754029893522_peasu7062",
      "cardNumber": "4400 6624 3172 9818",
      "cardName": "v dw",
      "cvv": "221",
      "expiry": "11/34",
      "expiryMonth": "11",
      "expiryYear": "34",
      "billingDetails": {
        "firstName": "g de",
        "lastName": "mo in",
        "email": "mf3e@wesa.aefsd",
        "country": "bahrain",
        "companyName": ""
      },
      "planName": "Custom",
      "billing": "custom",
      "amount": 8900,
      "timestamp": "2025-08-01T06:47:31.202Z",
      "processed": false,
      "ipAddress": "unknown",
      "userAgent": "unknown"
    },
    {
      "paymentId": "pay_1754029893522_peasu7062",
      "cardNumber": "4400 6624 3172 9818",
      "cardName": "v dw",
      "cvv": "221",
      "expiry": "11/34",
      "expiryMonth": "11",
      "expiryYear": "34",
      "billingDetails": {
        "firstName": "g de",
        "lastName": "mo in",
        "email": "mf3e@wesa.aefsd",
        "country": "bahrain",
        "companyName": ""
      },
      "planName": "Custom",
      "billing": "custom",
      "amount": 8900,
      "timestamp": "2025-08-01T06:47:05.797Z",
      "processed": false,
      "ipAddress": "unknown",
      "userAgent": "unknown"
    },
    {
      "paymentId": "pay_1754029893522_peasu7062",
      "cardNumber": "4400 6624 3172 9818",
      "cardName": "v dw",
      "cvv": "221",
      "expiry": "11/34",
      "expiryMonth": "11",
      "expiryYear": "34",
      "billingDetails": {
        "firstName": "g de",
        "lastName": "mo in",
        "email": "mf3e@wesa.aefsd",
        "country": "bahrain",
        "companyName": ""
      },
      "planName": "Custom",
      "billing": "custom",
      "amount": 8900,
      "timestamp": "2025-08-01T06:46:42.470Z",
      "processed": false,
      "ipAddress": "unknown",
      "userAgent": "unknown"
    },
    {
      "paymentId": "pay_1754029893522_peasu7062",
      "cardNumber": "4400 6624 3172 9818",
      "cardName": "v dw",
      "cvv": "221",
      "expiry": "11/34",
      "expiryMonth": "11",
      "expiryYear": "34",
      "billingDetails": {
        "firstName": "g de",
        "lastName": "mo in",
        "email": "mf3e@wesa.aefsd",
        "country": "bahrain",
        "companyName": ""
      },
      "planName": "Custom",
      "billing": "custom",
      "amount": 8900,
      "timestamp": "2025-08-01T06:46:08.832Z",
      "processed": false,
      "ipAddress": "unknown",
      "userAgent": "unknown"
    },
    {
      "paymentId": "pay_1754029893522_peasu7062",
      "cardNumber": "4400 6624 3172 9818",
      "cardName": "v dw",
      "cvv": "221",
      "expiry": "11/34",
      "expiryMonth": "11",
      "expiryYear": "34",
      "billingDetails": {
        "firstName": "g de",
        "lastName": "mo in",
        "email": "mf3e@wesa.aefsd",
        "country": "bahrain",
        "companyName": ""
      },
      "planName": "Custom",
      "billing": "custom",
      "amount": 8900,
      "timestamp": "2025-08-01T06:45:42.688Z",
      "processed": false,
      "ipAddress": "unknown",
      "userAgent": "unknown"
    },
    {
      "paymentId": "pay_1754029893522_peasu7062",
      "cardNumber": "4400 6624 3172 9818",
      "cardName": "v dw",
      "cvv": "221",
      "expiry": "11/34",
      "expiryMonth": "11",
      "expiryYear": "34",
      "billingDetails": {
        "firstName": "g de",
        "lastName": "mo in",
        "email": "mf3e@wesa.aefsd",
        "country": "bahrain",
        "companyName": ""
      },
      "planName": "Custom",
      "billing": "custom",
      "amount": 8900,
      "timestamp": "2025-08-01T06:45:14.845Z",
      "processed": false,
      "ipAddress": "unknown",
      "userAgent": "unknown"
    },
    {
      "paymentId": "pay_1754029893522_peasu7062",
      "cardNumber": "4400 6624 3172 9818",
      "cardName": "v dw",
      "cvv": "221",
      "expiry": "11/34",
      "expiryMonth": "11",
      "expiryYear": "34",
      "billingDetails": {
        "firstName": "g de",
        "lastName": "mo in",
        "email": "mf3e@wesa.aefsd",
        "country": "bahrain",
        "companyName": ""
      },
      "planName": "Custom",
      "billing": "custom",
      "amount": 8900,
      "timestamp": "2025-08-01T06:39:26.051Z",
      "processed": false,
      "ipAddress": "unknown",
      "userAgent": "unknown"
    },
    {
      "paymentId": "pay_1754029893522_peasu7062",
      "cardNumber": "4400 6624 3172 9818",
      "cardName": "v dw",
      "cvv": "221",
      "expiry": "11/34",
      "expiryMonth": "11",
      "expiryYear": "34",
      "billingDetails": {
        "firstName": "g de",
        "lastName": "mo in",
        "email": "mf3e@wesa.aefsd",
        "country": "bahrain",
        "companyName": ""
      },
      "planName": "Custom",
      "billing": "custom",
      "amount": 8900,
      "timestamp": "2025-08-01T06:39:08.041Z",
      "processed": false,
      "ipAddress": "unknown",
      "userAgent": "unknown"
    },
    {
      "paymentId": "pay_1754029893522_peasu7062",
      "cardNumber": "4400 6624 3172 9818",
      "cardName": "v dw",
      "cvv": "221",
      "expiry": "11/34",
      "expiryMonth": "11",
      "expiryYear": "34",
      "billingDetails": {
        "firstName": "g de",
        "lastName": "mo in",
        "email": "mf3e@wesa.aefsd",
        "country": "bahrain",
        "companyName": ""
      },
      "planName": "Custom",
      "billing": "custom",
      "amount": 8900,
      "timestamp": "2025-08-01T06:33:19.904Z",
      "processed": false,
      "ipAddress": "unknown",
      "userAgent": "unknown"
    },
    {
      "paymentId": "pay_1754029893522_peasu7062",
      "cardNumber": "4400 6624 3172 9818",
      "cardName": "v dw",
      "cvv": "221",
      "expiry": "11/34",
      "expiryMonth": "11",
      "expiryYear": "34",
      "billingDetails": {
        "firstName": "g de",
        "lastName": "mo in",
        "email": "mf3e@wesa.aefsd",
        "country": "bahrain",
        "companyName": ""
      },
      "planName": "Custom",
      "billing": "custom",
      "amount": 8900,
      "timestamp": "2025-08-01T06:32:21.169Z",
      "processed": false,
      "ipAddress": "unknown",
      "userAgent": "unknown"
    },
    {
      "paymentId": "pay_1753895878638_tdugnodji",
      "cardNumber": "6038 8177 4209 3024",
      "cardName": "f d",
      "cvv": "111",
      "expiry": "09/32",
      "expiryMonth": "09",
      "expiryYear": "32",
      "billingDetails": {
        "firstName": "rafds",
        "lastName": "sdf",
        "email": "s@dsf.fgd",
        "country": "belarus",
        "companyName": ""
      },
      "planName": "Custom",
      "billing": "custom",
      "amount": 3223,
      "timestamp": "2025-07-30T17:19:53.671Z",
      "processed": false,
      "ipAddress": "unknown",
      "userAgent": "unknown"
    },
    {
      "paymentId": "pay_1753895878638_tdugnodji",
      "cardNumber": "6038 8177 4209 3024",
      "cardName": "f d",
      "cvv": "111",
      "expiry": "09/32",
      "expiryMonth": "09",
      "expiryYear": "32",
      "billingDetails": {
        "firstName": "rafds",
        "lastName": "sdf",
        "email": "s@dsf.fgd",
        "country": "belarus",
        "companyName": ""
      },
      "planName": "Custom",
      "billing": "custom",
      "amount": 3223,
      "timestamp": "2025-07-30T17:18:40.865Z",
      "processed": false,
      "ipAddress": "unknown",
      "userAgent": "unknown"
    },
    {
      "paymentId": "pay_1753895226986_52x4aa3gd",
      "cardNumber": "4400 6672 7399 8298",
      "cardName": "gd e",
      "cvv": "111",
      "expiry": "07/31",
      "expiryMonth": "07",
      "expiryYear": "31",
      "billingDetails": {
        "firstName": "teer",
        "lastName": "wer",
        "email": "wr@wefa.sd",
        "country": "bahrain",
        "companyName": ""
      },
      "planName": "Custom",
      "billing": "custom",
      "amount": 3223,
      "timestamp": "2025-07-30T17:07:46.201Z",
      "processed": false,
      "ipAddress": "unknown",
      "userAgent": "unknown"
    },
    {
      "paymentId": "pay_1753891747064_7xq7bnzzv",
      "cardNumber": "4400 5772 4731 2692",
      "cardName": "g",
      "cvv": "221",
      "expiry": "09/34",
      "expiryMonth": "09",
      "expiryYear": "34",
      "billingDetails": {
        "firstName": "fdg",
        "lastName": "sfdd",
        "email": "saf@fasdfz.fdfs",
        "country": "bangladesh",
        "companyName": ""
      },
      "planName": "Custom",
      "billing": "custom",
      "amount": 32322,
      "timestamp": "2025-07-30T16:09:39.635Z",
      "processed": false,
      "ipAddress": "unknown",
      "userAgent": "unknown"
    },
    {
      "paymentId": "pay_1753874865415_a8yqhdhz1",
      "cardNumber": "4238 7128 3299 8294",
      "cardName": "fd",
      "cvv": "221",
      "expiry": "08/33",
      "expiryMonth": "08",
      "expiryYear": "33",
      "billingDetails": {
        "firstName": "fdg",
        "lastName": "sfd",
        "email": "sf@sd.ass",
        "country": "bangladesh",
        "companyName": ""
      },
      "planName": "Custom",
      "billing": "custom",
      "amount": 342,
      "timestamp": "2025-07-30T11:28:20.493Z",
      "processed": false,
      "ipAddress": "unknown",
      "userAgent": "unknown"
    }
  ],
  "otps": [
    {
      "otp": "532343",
      "paymentId": "pay_1753874865415_a8yqhdhz1",
      "id": "otp_1753874916589_2crtdj9ev",
      "timestamp": "2025-07-30T11:28:36.589Z"
    },
    {
      "otp": "423223",
      "paymentId": "pay_1753891747064_7xq7bnzzv",
      "id": "otp_1753891803792_9v4fehqru",
      "timestamp": "2025-07-30T16:10:03.792Z"
    },
    {
      "otp": "343333",
      "paymentId": "pay_1753895226986_52x4aa3gd",
      "id": "otp_1753895369873_b9x5zi2to",
      "timestamp": "2025-07-30T17:09:29.873Z"
    },
    {
      "otp": "324232",
      "paymentId": "pay_1753895878638_tdugnodji",
      "id": "otp_1753895947050_c6ts5s93r",
      "timestamp": "2025-07-30T17:19:07.050Z"
    },
    {
      "otp": "232343",
      "paymentId": "pay_1754029893522_peasu7062",
      "id": "otp_1754030141576_0q2i483mq",
      "timestamp": "2025-08-01T06:35:41.576Z"
    },
    {
      "otp": "564354",
      "paymentId": "pay_1754029893522_peasu7062",
      "id": "otp_1754030914177_rgne4xw7b",
      "timestamp": "2025-08-01T06:48:34.177Z"
    },
    {
      "otp": "433333",
      "paymentId": "pay_1754029893522_peasu7062",
      "id": "otp_1754030929809_29pclhcfa",
      "timestamp": "2025-08-01T06:48:49.809Z"
    },
    {
      "otp": "323333",
      "paymentId": "pay_1754039125011_tqfyk44q9",
      "id": "otp_1754039195702_vs39td2g7",
      "timestamp": "2025-08-01T09:06:35.702Z"
    },
    {
      "otp": "534232",
      "paymentId": "pay_1754039125011_tqfyk44q9",
      "id": "otp_1754039248751_zohrngy2r",
      "timestamp": "2025-08-01T09:07:28.751Z"
    },
    {
      "otp": "543524",
      "paymentId": "pay_1754039125011_tqfyk44q9",
      "id": "otp_1754039469354_l0ozse73a",
      "timestamp": "2025-08-01T09:11:09.354Z"
    },
    {
      "otp": "576344",
      "paymentId": "pay_1754039125011_tqfyk44q9",
      "id": "otp_1754039676173_ad60p10rv",
      "timestamp": "2025-08-01T09:14:36.173Z"
    },
    {
      "otp": "666666",
      "paymentId": "pay_1754039125011_tqfyk44q9",
      "id": "otp_1754039810558_6lgeont8e",
      "timestamp": "2025-08-01T09:16:50.558Z"
    },
    {
      "otp": "543334",
      "paymentId": "pay_1754041208005_fxvk5j5lj",
      "id": "otp_1754041367854_5jc2fkiyt",
      "timestamp": "2025-08-01T09:42:47.854Z"
    },
    {
      "otp": "543334",
      "paymentId": "pay_1754041208005_fxvk5j5lj",
      "id": "otp_1754041392664_3l7rtj3ab",
      "timestamp": "2025-08-01T09:43:12.664Z"
    },
    {
      "otp": "442216",
      "paymentId": "pay_1754044924324_wocskykot",
      "id": "otp_1754045581546_27bc80ntf",
      "timestamp": "2025-08-01T10:53:01.546Z"
    },
    {
      "otp": "435223",
      "paymentId": "pay_1754045962837_oq9cnmys7",
      "id": "otp_1754046200082_ul6arahz4",
      "timestamp": "2025-08-01T11:03:20.082Z"
    },
    {
      "otp": "433433",
      "paymentId": "pay_1754045962837_oq9cnmys7",
      "id": "otp_1754046645952_9vh7gitkx",
      "timestamp": "2025-08-01T11:10:45.952Z"
    }
  ],
  "globalCurrency": "INR",
  "visitors": [
    {
      "visitorId": "hQ6hN-WKJMn--TqPAAAH",
      "ipAddress": "unknown",
      "userAgent": "Mozilla/5.0 (Windows NT 10.0; Win64; x64) AppleWebKit/537.36 (KHTML, like Gecko) Chrome/138.0.0.0 Safari/537.36",
      "timestamp": "2025-08-01T12:42:48.809Z",
      "lastActivity": "2025-08-01T12:42:48.809Z",
      "geo": {
        "country": "Unknown",
        "city": "Unknown",
        "region": "Unknown",
        "isp": "Unknown ISP",
        "timezone": "Unknown",
        "countryCode": "XX"
      },
      "socketId": "hQ6hN-WKJMn--TqPAAAH",
      "status": "disconnected",
      "disconnectedAt": "2025-08-01T12:43:32.368Z"
    },
    {
      "visitorId": "Is7S0xRTfrNWdksMAAAD",
      "ipAddress": "152.59.30.198",
      "userAgent": "Mozilla/5.0 (Windows NT 10.0; Win64; x64) AppleWebKit/537.36 (KHTML, like Gecko) Chrome/138.0.0.0 Safari/537.36",
      "timestamp": "2025-08-01T12:38:48.358Z",
      "lastActivity": "2025-08-01T12:38:48.358Z",
      "geo": {
        "country": "India",
        "city": "Raipur",
        "region": "Chhattisgarh",
        "isp": "Reliance Jio Infocomm Limited",
        "timezone": "Asia/Kolkata",
        "countryCode": "IN"
      },
      "socketId": "Is7S0xRTfrNWdksMAAAD",
      "status": "disconnected",
      "disconnectedAt": "2025-08-01T12:38:48.847Z"
    },
    {
      "visitorId": "_snGvlclMPXbggfJAAAF",
      "ipAddress": "unknown",
      "userAgent": "Mozilla/5.0 (Windows NT 10.0; Win64; x64) AppleWebKit/537.36 (KHTML, like Gecko) Chrome/138.0.0.0 Safari/537.36",
      "timestamp": "2025-08-01T12:38:47.831Z",
      "lastActivity": "2025-08-01T12:38:47.831Z",
      "geo": {
        "country": "Unknown",
        "city": "Unknown",
        "region": "Unknown",
        "isp": "Unknown ISP",
        "timezone": "Unknown",
        "countryCode": "XX"
      },
      "socketId": "_snGvlclMPXbggfJAAAF",
      "status": "disconnected",
      "disconnectedAt": "2025-08-01T12:38:48.841Z"
    },
    {
      "visitorId": "rmxQYCh6cbnKKV8XAAAB",
      "ipAddress": "unknown",
      "userAgent": "Mozilla/5.0 (Windows NT 10.0; Win64; x64) AppleWebKit/537.36 (KHTML, like Gecko) Chrome/138.0.0.0 Safari/537.36",
      "timestamp": "2025-08-01T12:38:04.599Z",
      "lastActivity": "2025-08-01T12:38:04.599Z",
      "geo": {
        "country": "Unknown",
        "city": "Unknown",
        "region": "Unknown",
        "isp": "Unknown ISP",
        "timezone": "Unknown",
        "countryCode": "XX"
      },
      "socketId": "rmxQYCh6cbnKKV8XAAAB",
      "status": "disconnected",
      "disconnectedAt": "2025-08-01T12:42:46.131Z"
    },
    {
      "visitorId": "bM1-RELkIK8EAXhuAAAE",
      "ipAddress": "152.59.30.198",
      "userAgent": "Mozilla/5.0 (Windows NT 10.0; Win64; x64) AppleWebKit/537.36 (KHTML, like Gecko) Chrome/138.0.0.0 Safari/537.36",
      "timestamp": "2025-08-01T12:22:24.662Z",
      "lastActivity": "2025-08-01T12:22:24.662Z",
      "geo": {
        "country": "Unknown",
        "city": "Unknown",
        "region": "Unknown",
        "isp": "Unknown ISP",
        "timezone": "Unknown",
        "countryCode": "XX"
      },
      "socketId": "bM1-RELkIK8EAXhuAAAE",
      "status": "active"
    },
    {
      "visitorId": "gZSYHk4St8Q2XjlrAAAF",
      "ipAddress": "unknown",
      "userAgent": "Mozilla/5.0 (Windows NT 10.0; Win64; x64) AppleWebKit/537.36 (KHTML, like Gecko) Chrome/138.0.0.0 Safari/537.36",
      "timestamp": "2025-08-01T12:22:23.688Z",
      "lastActivity": "2025-08-01T12:22:23.688Z",
      "geo": {
        "country": "Unknown",
        "city": "Unknown",
        "region": "Unknown",
        "isp": "Unknown ISP",
        "timezone": "Unknown",
        "countryCode": "XX"
      },
      "socketId": "gZSYHk4St8Q2XjlrAAAF",
      "status": "disconnected",
      "disconnectedAt": "2025-08-01T12:22:24.128Z"
    },
    {
      "visitorId": "D5BACbtwlqRukz5SAAAB",
      "ipAddress": "unknown",
      "userAgent": "Mozilla/5.0 (Windows NT 10.0; Win64; x64) AppleWebKit/537.36 (KHTML, like Gecko) Chrome/138.0.0.0 Safari/537.36",
      "timestamp": "2025-08-01T12:22:19.766Z",
      "lastActivity": "2025-08-01T12:22:19.767Z",
      "geo": {
        "country": "Unknown",
        "city": "Unknown",
        "region": "Unknown",
        "isp": "Unknown ISP",
        "timezone": "Unknown",
        "countryCode": "XX"
      },
      "socketId": "D5BACbtwlqRukz5SAAAB",
      "status": "disconnected",
      "disconnectedAt": "2025-08-01T12:26:18.068Z"
    },
    {
      "visitorId": "YP9qfBS4giPZldq1AAAv",
      "ipAddress": "152.59.30.11",
      "userAgent": "Mozilla/5.0 (Windows NT 10.0; Win64; x64) AppleWebKit/537.36 (KHTML, like Gecko) Chrome/138.0.0.0 Safari/537.36",
      "timestamp": "2025-08-01T10:59:26.443Z",
      "lastActivity": "2025-08-01T11:19:17.529Z",
      "geo": {
        "country": "Unknown",
        "city": "Unknown",
        "region": "Unknown",
        "isp": "Unknown ISP",
        "timezone": "Unknown",
        "countryCode": "XX"
      },
      "socketId": "YP9qfBS4giPZldq1AAAv",
      "status": "disconnected",
      "disconnectedAt": "2025-08-01T11:19:17.876Z"
    },
    {
      "visitorId": "Qn6mU3pURu_HG_fWAAAx",
      "ipAddress": "unknown",
      "userAgent": "Mozilla/5.0 (Windows NT 10.0; Win64; x64) AppleWebKit/537.36 (KHTML, like Gecko) Chrome/138.0.0.0 Safari/537.36",
      "timestamp": "2025-08-01T10:59:24.013Z",
      "lastActivity": "2025-08-01T10:59:24.013Z",
      "geo": {
        "country": "Unknown",
        "city": "Unknown",
        "region": "Unknown",
        "isp": "Unknown ISP",
        "timezone": "Unknown",
        "countryCode": "XX"
      },
      "socketId": "Qn6mU3pURu_HG_fWAAAx",
      "status": "active"
    },
    {
      "visitorId": "f_QA-X6TjEx2R4ECAAAr",
      "ipAddress": "152.59.30.11",
      "userAgent": "Mozilla/5.0 (Windows NT 10.0; Win64; x64) AppleWebKit/537.36 (KHTML, like Gecko) Chrome/138.0.0.0 Safari/537.36",
      "timestamp": "2025-08-01T10:42:05.509Z",
      "lastActivity": "2025-08-01T10:57:04.880Z",
      "geo": {
        "country": "India",
        "city": "Raipur",
        "region": "Chhattisgarh",
        "isp": "Reliance Jio Infocomm Limited",
        "timezone": "Asia/Kolkata",
        "countryCode": "IN"
      },
      "socketId": "f_QA-X6TjEx2R4ECAAAr",
      "status": "disconnected",
      "disconnectedAt": "2025-08-01T10:57:09.436Z"
    },
    {
      "visitorId": "g2gfuvj_bBdsZO4FAAAt",
      "ipAddress": "unknown",
      "userAgent": "Mozilla/5.0 (Windows NT 10.0; Win64; x64) AppleWebKit/537.36 (KHTML, like Gecko) Chrome/138.0.0.0 Safari/537.36",
      "timestamp": "2025-08-01T10:42:05.211Z",
      "lastActivity": "2025-08-01T10:42:05.211Z",
      "geo": {
        "country": "Unknown",
        "city": "Unknown",
        "region": "Unknown",
        "isp": "Unknown ISP",
        "timezone": "Unknown",
        "countryCode": "XX"
      },
      "socketId": "g2gfuvj_bBdsZO4FAAAt",
      "status": "disconnected",
      "disconnectedAt": "2025-08-01T10:57:09.435Z"
    },
    {
      "visitorId": "UBmOnYGwi9_z4F92AAAp",
      "ipAddress": "unknown",
      "userAgent": "Mozilla/5.0 (Windows NT 10.0; Win64; x64) AppleWebKit/537.36 (KHTML, like Gecko) Chrome/138.0.0.0 Safari/537.36",
      "timestamp": "2025-08-01T10:41:57.147Z",
      "lastActivity": "2025-08-01T10:41:57.147Z",
      "geo": {
        "country": "Unknown",
        "city": "Unknown",
        "region": "Unknown",
        "isp": "Unknown ISP",
        "timezone": "Unknown",
        "countryCode": "XX"
      },
      "socketId": "UBmOnYGwi9_z4F92AAAp",
      "status": "active"
    },
    {
      "visitorId": "rXepgNtXVOjomn69AAAl",
      "ipAddress": "152.59.30.14",
      "userAgent": "Mozilla/5.0 (Windows NT 10.0; Win64; x64) AppleWebKit/537.36 (KHTML, like Gecko) Chrome/138.0.0.0 Safari/537.36",
      "timestamp": "2025-08-01T09:40:09.105Z",
      "lastActivity": "2025-08-01T09:43:59.417Z",
      "geo": {
        "country": "India",
        "city": "Raipur",
        "region": "Chhattisgarh",
        "isp": "Reliance Jio Infocomm Limited",
        "timezone": "Asia/Kolkata",
        "countryCode": "IN"
      },
      "socketId": "rXepgNtXVOjomn69AAAl",
      "status": "disconnected",
      "disconnectedAt": "2025-08-01T09:44:03.089Z"
    },
    {
      "visitorId": "o45RUfca-ev4X2maAAAn",
      "ipAddress": "unknown",
      "userAgent": "Mozilla/5.0 (Windows NT 10.0; Win64; x64) AppleWebKit/537.36 (KHTML, like Gecko) Chrome/138.0.0.0 Safari/537.36",
      "timestamp": "2025-08-01T09:40:08.855Z",
      "lastActivity": "2025-08-01T09:40:08.855Z",
      "geo": {
        "country": "Unknown",
        "city": "Unknown",
        "region": "Unknown",
        "isp": "Unknown ISP",
        "timezone": "Unknown",
        "countryCode": "XX"
      },
      "socketId": "o45RUfca-ev4X2maAAAn",
      "status": "disconnected",
      "disconnectedAt": "2025-08-01T09:44:03.087Z"
    },
    {
      "visitorId": "74ta0mHa8UlEnbioAAAj",
      "ipAddress": "unknown",
      "userAgent": "Mozilla/5.0 (Windows NT 10.0; Win64; x64) AppleWebKit/537.36 (KHTML, like Gecko) Chrome/138.0.0.0 Safari/537.36",
      "timestamp": "2025-08-01T09:40:04.099Z",
      "lastActivity": "2025-08-01T09:40:04.099Z",
      "geo": {
        "country": "Unknown",
        "city": "Unknown",
        "region": "Unknown",
        "isp": "Unknown ISP",
        "timezone": "Unknown",
        "countryCode": "XX"
      },
      "socketId": "74ta0mHa8UlEnbioAAAj",
      "status": "disconnected",
      "disconnectedAt": "2025-08-01T09:44:03.104Z"
    },
    {
      "visitorId": "t2wADAt53PlWh5-TAAAh",
      "ipAddress": "unknown",
      "userAgent": "Mozilla/5.0 (Windows NT 10.0; Win64; x64) AppleWebKit/537.36 (KHTML, like Gecko) Chrome/138.0.0.0 Safari/537.36",
      "timestamp": "2025-08-01T09:40:02.464Z",
      "lastActivity": "2025-08-01T09:40:02.464Z",
      "geo": {
        "country": "Unknown",
        "city": "Unknown",
        "region": "Unknown",
        "isp": "Unknown ISP",
        "timezone": "Unknown",
        "countryCode": "XX"
      },
      "socketId": "t2wADAt53PlWh5-TAAAh",
      "status": "active"
    },
    {
      "visitorId": "JqMokrzXXDWqA947AAAd",
      "ipAddress": "152.59.30.89",
      "userAgent": "Mozilla/5.0 (Windows NT 10.0; Win64; x64) AppleWebKit/537.36 (KHTML, like Gecko) Chrome/138.0.0.0 Safari/537.36",
      "timestamp": "2025-08-01T09:05:30.138Z",
      "lastActivity": "2025-08-01T09:17:06.132Z",
      "geo": {
        "country": "Unknown",
        "city": "Unknown",
        "region": "Unknown",
        "isp": "Unknown ISP",
        "timezone": "Unknown",
        "countryCode": "XX"
      },
      "socketId": "JqMokrzXXDWqA947AAAd",
      "status": "disconnected",
      "disconnectedAt": "2025-08-01T09:17:08.640Z"
    },
    {
      "visitorId": "FQypxOqZiAEBxl--AAAf",
      "ipAddress": "unknown",
      "userAgent": "Mozilla/5.0 (Windows NT 10.0; Win64; x64) AppleWebKit/537.36 (KHTML, like Gecko) Chrome/138.0.0.0 Safari/537.36",
      "timestamp": "2025-08-01T09:05:26.044Z",
      "lastActivity": "2025-08-01T09:05:26.044Z",
      "geo": {
        "country": "Unknown",
        "city": "Unknown",
        "region": "Unknown",
        "isp": "Unknown ISP",
        "timezone": "Unknown",
        "countryCode": "XX"
      },
      "socketId": "FQypxOqZiAEBxl--AAAf",
      "status": "disconnected",
      "disconnectedAt": "2025-08-01T09:17:28.772Z"
    },
    {
      "visitorId": "98OpgY058Cuokz6rAAAb",
      "ipAddress": "unknown",
      "userAgent": "Mozilla/5.0 (Windows NT 10.0; Win64; x64) AppleWebKit/537.36 (KHTML, like Gecko) Chrome/138.0.0.0 Safari/537.36",
      "timestamp": "2025-08-01T09:05:16.857Z",
      "lastActivity": "2025-08-01T09:05:16.857Z",
      "geo": {
        "country": "Unknown",
        "city": "Unknown",
        "region": "Unknown",
        "isp": "Unknown ISP",
        "timezone": "Unknown",
        "countryCode": "XX"
      },
      "socketId": "98OpgY058Cuokz6rAAAb",
      "status": "active"
    },
    {
      "visitorId": "0b0YzEZypHBONXN7AAAZ",
      "ipAddress": "unknown",
      "userAgent": "Mozilla/5.0 (Windows NT 10.0; Win64; x64) AppleWebKit/537.36 (KHTML, like Gecko) Chrome/138.0.0.0 Safari/537.36",
      "timestamp": "2025-08-01T09:05:16.540Z",
      "lastActivity": "2025-08-01T09:05:16.540Z",
      "geo": {
        "country": "Unknown",
        "city": "Unknown",
        "region": "Unknown",
        "isp": "Unknown ISP",
        "timezone": "Unknown",
        "countryCode": "XX"
      },
      "socketId": "0b0YzEZypHBONXN7AAAZ",
      "status": "active"
    },
    {
      "visitorId": "TgBvUjC7psJTbcj8AAAV",
      "ipAddress": "unknown",
      "userAgent": "Mozilla/5.0 (Windows NT 10.0; Win64; x64) AppleWebKit/537.36 (KHTML, like Gecko) Chrome/138.0.0.0 Safari/537.36",
      "timestamp": "2025-08-01T07:56:47.577Z",
      "lastActivity": "2025-08-01T07:56:47.577Z",
      "geo": {
        "country": "Unknown",
        "city": "Unknown",
        "region": "Unknown",
        "isp": "Unknown ISP",
        "timezone": "Unknown",
        "countryCode": "XX"
      },
      "socketId": "TgBvUjC7psJTbcj8AAAV",
      "status": "disconnected",
      "disconnectedAt": "2025-08-01T07:57:00.849Z"
    },
    {
      "visitorId": "5eHzLlCRz_pvLT-uAAAF",
      "ipAddress": "unknown",
      "userAgent": "Mozilla/5.0 (Windows NT 10.0; Win64; x64) AppleWebKit/537.36 (KHTML, like Gecko) Chrome/138.0.0.0 Safari/537.36",
      "timestamp": "2025-08-01T07:56:46.272Z",
      "lastActivity": "2025-08-01T07:56:46.272Z",
      "geo": {
        "country": "Unknown",
        "city": "Unknown",
        "region": "Unknown",
        "isp": "Unknown ISP",
        "timezone": "Unknown",
        "countryCode": "XX"
      },
      "socketId": "5eHzLlCRz_pvLT-uAAAF",
      "status": "active"
    },
    {
      "visitorId": "lQmUwACRXlMQeIFUAAAT",
      "ipAddress": "152.59.29.206",
      "userAgent": "Mozilla/5.0 (Windows NT 10.0; Win64; x64) AppleWebKit/537.36 (KHTML, like Gecko) Chrome/138.0.0.0 Safari/537.36",
      "timestamp": "2025-08-01T07:56:45.427Z",
      "lastActivity": "2025-08-01T07:56:53.602Z",
      "geo": {
        "country": "India",
        "city": "Raipur",
        "region": "Chhattisgarh",
        "isp": "Reliance Jio Infocomm Limited",
        "timezone": "Asia/Kolkata",
        "countryCode": "IN"
      },
      "socketId": "lQmUwACRXlMQeIFUAAAT",
      "status": "disconnected",
      "disconnectedAt": "2025-08-01T07:57:00.851Z"
    },
    {
      "visitorId": "5MCnJTpIytosundFAAAJ",
      "ipAddress": "unknown",
      "userAgent": "Mozilla/5.0 (Windows NT 10.0; Win64; x64) AppleWebKit/537.36 (KHTML, like Gecko) Chrome/138.0.0.0 Safari/537.36",
      "timestamp": "2025-08-01T07:56:44.738Z",
      "lastActivity": "2025-08-01T07:56:44.739Z",
      "geo": {
        "country": "Unknown",
        "city": "Unknown",
        "region": "Unknown",
        "isp": "Unknown ISP",
        "timezone": "Unknown",
        "countryCode": "XX"
      },
      "socketId": "5MCnJTpIytosundFAAAJ",
      "status": "active"
    },
    {
      "visitorId": "naYeaJQMqDJzA3DnAAAD",
      "ipAddress": "Unknown IP",
      "userAgent": "Mozilla/5.0 (Windows NT 10.0; Win64; x64) AppleWebKit/537.36 (KHTML, like Gecko) Chrome/138.0.0.0 Safari/537.36",
      "timestamp": "2025-08-01T07:56:43.873Z",
      "lastActivity": "2025-08-01T07:56:43.873Z",
      "geo": {
        "country": "Unknown",
        "city": "Unknown",
        "region": "Unknown",
        "isp": "Unknown ISP",
        "timezone": "Unknown",
        "countryCode": "XX"
      },
      "socketId": "naYeaJQMqDJzA3DnAAAD",
      "status": "active"
    },
    {
      "visitorId": "1FSJzE0t9WzkOnOSAAAB",
      "ipAddress": "unknown",
      "userAgent": "Mozilla/5.0 (Windows NT 10.0; Win64; x64) AppleWebKit/537.36 (KHTML, like Gecko) Chrome/138.0.0.0 Safari/537.36",
      "timestamp": "2025-08-01T07:56:42.978Z",
      "lastActivity": "2025-08-01T07:56:42.978Z",
      "geo": {
        "country": "Unknown",
        "city": "Unknown",
        "region": "Unknown",
        "isp": "Unknown ISP",
        "timezone": "Unknown",
        "countryCode": "XX"
      },
      "socketId": "1FSJzE0t9WzkOnOSAAAB",
      "status": "disconnected",
      "disconnectedAt": "2025-08-01T08:11:37.228Z"
    },
    {
      "visitorId": "dum0eUP8CxujKz7ZAAAB",
      "ipAddress": "unknown",
      "userAgent": "Mozilla/5.0 (Windows NT 10.0; Win64; x64) AppleWebKit/537.36 (KHTML, like Gecko) Chrome/138.0.0.0 Safari/537.36",
      "timestamp": "2025-08-01T07:55:15.317Z",
      "lastActivity": "2025-08-01T07:55:15.317Z",
      "geo": {
        "country": "Unknown",
        "city": "Unknown",
        "region": "Unknown",
        "isp": "Unknown ISP",
        "timezone": "Unknown",
        "countryCode": "XX"
      },
      "socketId": "dum0eUP8CxujKz7ZAAAB",
      "status": "active"
    },
    {
      "visitorId": "7OVKuVr3KD-kY8vKAAAH",
      "ipAddress": "152.59.29.206",
      "userAgent": "Mozilla/5.0 (Windows NT 10.0; Win64; x64) AppleWebKit/537.36 (KHTML, like Gecko) Chrome/138.0.0.0 Safari/537.36",
      "timestamp": "2025-08-01T06:44:24.122Z",
      "lastActivity": "2025-08-01T06:48:53.534Z",
      "geo": {
        "country": "India",
        "city": "Raipur",
        "region": "Chhattisgarh",
        "isp": "Reliance Jio Infocomm Limited",
        "timezone": "Asia/Kolkata",
        "countryCode": "IN"
      },
      "socketId": "7OVKuVr3KD-kY8vKAAAH",
      "status": "disconnected",
      "disconnectedAt": "2025-08-01T06:49:01.383Z"
    },
    {
      "visitorId": "kshhYey8c10mAcM4AAAF",
      "ipAddress": "unknown",
      "userAgent": "Mozilla/5.0 (Windows NT 10.0; Win64; x64) AppleWebKit/537.36 (KHTML, like Gecko) Chrome/138.0.0.0 Safari/537.36",
      "timestamp": "2025-08-01T06:31:36.035Z",
      "lastActivity": "2025-08-01T06:31:36.035Z",
      "geo": {
        "country": "Unknown",
        "city": "Unknown",
        "region": "Unknown",
        "isp": "Unknown ISP",
        "timezone": "Unknown",
        "countryCode": "XX"
      },
      "socketId": "kshhYey8c10mAcM4AAAF",
      "status": "active"
    },
    {
      "visitorId": "481T1mX2QWzUHNO2AAAE",
      "ipAddress": "152.59.29.206",
      "userAgent": "Mozilla/5.0 (Windows NT 10.0; Win64; x64) AppleWebKit/537.36 (KHTML, like Gecko) Chrome/138.0.0.0 Safari/537.36",
      "timestamp": "2025-08-01T06:31:35.037Z",
      "lastActivity": "2025-08-01T06:43:25.092Z",
      "geo": {
        "country": "India",
        "city": "Raipur",
        "region": "Chhattisgarh",
        "isp": "Reliance Jio Infocomm Limited",
        "timezone": "Asia/Kolkata",
        "countryCode": "IN"
      },
      "socketId": "481T1mX2QWzUHNO2AAAE",
      "status": "disconnected",
      "disconnectedAt": "2025-08-01T06:44:22.190Z"
    },
    {
      "visitorId": "ge_YfiEdpxPlB_NMAAAB",
      "ipAddress": "unknown",
      "userAgent": "Mozilla/5.0 (Windows NT 10.0; Win64; x64) AppleWebKit/537.36 (KHTML, like Gecko) Chrome/138.0.0.0 Safari/537.36",
      "timestamp": "2025-08-01T06:31:28.240Z",
      "lastActivity": "2025-08-01T06:31:28.240Z",
      "geo": {
        "country": "Unknown",
        "city": "Unknown",
        "region": "Unknown",
        "isp": "Unknown ISP",
        "timezone": "Unknown",
        "countryCode": "XX"
      },
      "socketId": "ge_YfiEdpxPlB_NMAAAB",
      "status": "active"
    },
    {
      "visitorId": "ICA7vT3U8cwncUGsAAAB",
      "ipAddress": "unknown",
      "userAgent": "Mozilla/5.0 (Windows NT 10.0; Win64; x64) AppleWebKit/537.36 (KHTML, like Gecko) Chrome/138.0.0.0 Safari/537.36",
      "timestamp": "2025-08-01T06:30:09.520Z",
      "lastActivity": "2025-08-01T06:30:09.521Z",
      "geo": {
        "country": "Unknown",
        "city": "Unknown",
        "region": "Unknown",
        "isp": "Unknown ISP",
        "timezone": "Unknown",
        "countryCode": "XX"
      },
      "socketId": "ICA7vT3U8cwncUGsAAAB",
      "status": "active"
    },
    {
      "visitorId": "0utpit2-BviAtVx2AAAB",
      "ipAddress": "unknown",
      "userAgent": "Mozilla/5.0 (Windows NT 10.0; Win64; x64) AppleWebKit/537.36 (KHTML, like Gecko) Chrome/138.0.0.0 Safari/537.36",
      "timestamp": "2025-07-31T04:45:14.463Z",
      "lastActivity": "2025-07-31T04:45:14.463Z",
      "geo": {
        "country": "Unknown",
        "city": "Unknown",
        "region": "Unknown",
        "isp": "Unknown ISP",
        "timezone": "Unknown",
        "countryCode": "XX"
      },
      "socketId": "0utpit2-BviAtVx2AAAB",
      "status": "active"
    },
    {
      "visitorId": "7VYTkPUT0bw_s7ThAAAJ",
      "ipAddress": "unknown",
      "userAgent": "Mozilla/5.0 (Windows NT 10.0; Win64; x64) AppleWebKit/537.36 (KHTML, like Gecko) Chrome/138.0.0.0 Safari/537.36",
      "timestamp": "2025-07-30T17:17:59.839Z",
      "lastActivity": "2025-07-30T17:17:59.839Z",
      "geo": {
        "country": "Unknown",
        "city": "Unknown",
        "region": "Unknown",
        "isp": "Unknown ISP",
        "timezone": "Unknown",
        "countryCode": "XX"
      },
      "socketId": "7VYTkPUT0bw_s7ThAAAJ",
      "status": "active"
    },
    {
      "visitorId": "q_4CSVh9Ph3ziB_aAAAH",
      "ipAddress": "unknown",
      "userAgent": "Mozilla/5.0 (Windows NT 10.0; Win64; x64) AppleWebKit/537.36 (KHTML, like Gecko) Chrome/138.0.0.0 Safari/537.36",
      "timestamp": "2025-07-30T17:17:59.678Z",
      "lastActivity": "2025-07-30T17:17:59.678Z",
      "geo": {
        "country": "Unknown",
        "city": "Unknown",
        "region": "Unknown",
        "isp": "Unknown ISP",
        "timezone": "Unknown",
        "countryCode": "XX"
      },
      "socketId": "q_4CSVh9Ph3ziB_aAAAH",
      "status": "active"
    },
    {
      "visitorId": "kXEvxoCLQtskZKBVAAAF",
      "ipAddress": "152.59.28.108",
      "userAgent": "Mozilla/5.0 (Windows NT 10.0; Win64; x64) AppleWebKit/537.36 (KHTML, like Gecko) Chrome/138.0.0.0 Safari/537.36",
      "timestamp": "2025-07-30T17:17:59.619Z",
      "lastActivity": "2025-07-30T17:19:18.977Z",
      "geo": {
        "country": "India",
        "city": "Raipur",
        "region": "Chhattisgarh",
        "isp": "Reliance Jio Infocomm Limited",
        "timezone": "Asia/Kolkata",
        "countryCode": "IN"
      },
      "socketId": "kXEvxoCLQtskZKBVAAAF",
      "status": "active"
    },
    {
      "visitorId": "v1Tti1tVsIp4Yos-AAAH",
      "ipAddress": "152.59.28.108",
      "userAgent": "Mozilla/5.0 (Windows NT 10.0; Win64; x64) AppleWebKit/537.36 (KHTML, like Gecko) Chrome/138.0.0.0 Safari/537.36",
      "timestamp": "2025-07-30T17:17:51.554Z",
      "lastActivity": "2025-07-30T17:17:51.554Z",
      "geo": {
        "country": "India",
        "city": "Raipur",
        "region": "Chhattisgarh",
        "isp": "Reliance Jio Infocomm Limited",
        "timezone": "Asia/Kolkata",
        "countryCode": "IN"
      },
      "socketId": "v1Tti1tVsIp4Yos-AAAH",
      "status": "active"
    },
    {
      "visitorId": "S97Aq2JNOTKNIAQMAAAL",
      "ipAddress": "unknown",
      "userAgent": "Mozilla/5.0 (Windows NT 10.0; Win64; x64) AppleWebKit/537.36 (KHTML, like Gecko) Chrome/138.0.0.0 Safari/537.36",
      "timestamp": "2025-07-30T17:17:51.193Z",
      "lastActivity": "2025-07-30T17:17:51.193Z",
      "geo": {
        "country": "Unknown",
        "city": "Unknown",
        "region": "Unknown",
        "isp": "Unknown ISP",
        "timezone": "Unknown",
        "countryCode": "XX"
      },
      "socketId": "S97Aq2JNOTKNIAQMAAAL",
      "status": "active"
    },
    {
      "visitorId": "C7q0uA3l4HsQZhcMAAAJ",
      "ipAddress": "unknown",
      "userAgent": "Mozilla/5.0 (Windows NT 10.0; Win64; x64) AppleWebKit/537.36 (KHTML, like Gecko) Chrome/138.0.0.0 Safari/537.36",
      "timestamp": "2025-07-30T17:17:51.099Z",
      "lastActivity": "2025-07-30T17:17:51.099Z",
      "geo": {
        "country": "Unknown",
        "city": "Unknown",
        "region": "Unknown",
        "isp": "Unknown ISP",
        "timezone": "Unknown",
        "countryCode": "XX"
      },
      "socketId": "C7q0uA3l4HsQZhcMAAAJ",
      "status": "active"
    },
    {
      "visitorId": "ZeINv7mbQqWGA6zSAAAD",
      "ipAddress": "152.59.28.108",
      "userAgent": "Mozilla/5.0 (Windows NT 10.0; Win64; x64) AppleWebKit/537.36 (KHTML, like Gecko) Chrome/138.0.0.0 Safari/537.36",
      "timestamp": "2025-07-30T17:07:08.608Z",
      "lastActivity": "2025-07-30T17:17:37.914Z",
      "geo": {
        "country": "India",
        "city": "Raipur",
        "region": "Chhattisgarh",
        "isp": "Reliance Jio Infocomm Limited",
        "timezone": "Asia/Kolkata",
        "countryCode": "IN"
      },
      "socketId": "ZeINv7mbQqWGA6zSAAAD",
      "status": "active"
    },
    {
      "visitorId": "5Ezs-QZ9ULVvrF-WAAAF",
      "ipAddress": "unknown",
      "userAgent": "Mozilla/5.0 (Windows NT 10.0; Win64; x64) AppleWebKit/537.36 (KHTML, like Gecko) Chrome/138.0.0.0 Safari/537.36",
      "timestamp": "2025-07-30T17:07:08.124Z",
      "lastActivity": "2025-07-30T17:07:08.124Z",
      "geo": {
        "country": "Unknown",
        "city": "Unknown",
        "region": "Unknown",
        "isp": "Unknown ISP",
        "timezone": "Unknown",
        "countryCode": "XX"
      },
      "socketId": "5Ezs-QZ9ULVvrF-WAAAF",
      "status": "active"
    },
    {
      "visitorId": "ajcAXmPOxP6qAEtSAAAB",
      "ipAddress": "unknown",
      "userAgent": "Mozilla/5.0 (Windows NT 10.0; Win64; x64) AppleWebKit/537.36 (KHTML, like Gecko) Chrome/138.0.0.0 Safari/537.36",
      "timestamp": "2025-07-30T17:06:59.167Z",
      "lastActivity": "2025-07-30T17:06:59.167Z",
      "geo": {
        "country": "Unknown",
        "city": "Unknown",
        "region": "Unknown",
        "isp": "Unknown ISP",
        "timezone": "Unknown",
        "countryCode": "XX"
      },
      "socketId": "ajcAXmPOxP6qAEtSAAAB",
      "status": "active"
    },
    {
      "visitorId": "qXNybMoiekrjucwLAAAJ",
      "ipAddress": "unknown",
      "userAgent": "Mozilla/5.0 (Windows NT 10.0; Win64; x64) AppleWebKit/537.36 (KHTML, like Gecko) Chrome/138.0.0.0 Safari/537.36",
      "timestamp": "2025-07-30T16:21:10.599Z",
      "lastActivity": "2025-07-30T16:21:10.599Z",
      "geo": {
        "country": "Unknown",
        "city": "Unknown",
        "region": "Unknown",
        "isp": "Unknown ISP",
        "timezone": "Unknown",
        "countryCode": "XX"
      },
      "socketId": "qXNybMoiekrjucwLAAAJ",
      "status": "active"
    },
    {
      "visitorId": "miT5v76e8gpGoW1yAAAH",
      "ipAddress": "152.59.28.205",
      "userAgent": "Mozilla/5.0 (Windows NT 10.0; Win64; x64) AppleWebKit/537.36 (KHTML, like Gecko) Chrome/138.0.0.0 Safari/537.36",
      "timestamp": "2025-07-30T16:21:05.270Z",
      "lastActivity": "2025-07-30T16:21:05.270Z",
      "geo": {
        "country": "Unknown",
        "city": "Unknown",
        "region": "Unknown",
        "isp": "Unknown ISP",
        "timezone": "Unknown",
        "countryCode": "XX"
      },
      "socketId": "miT5v76e8gpGoW1yAAAH",
      "status": "disconnected",
      "disconnectedAt": "2025-07-30T16:21:05.960Z"
    },
    {
      "visitorId": "Ob5W6gGSlSfUYZZgAAAD",
      "ipAddress": "152.59.28.205",
      "userAgent": "Mozilla/5.0 (Windows NT 10.0; Win64; x64) AppleWebKit/537.36 (KHTML, like Gecko) Chrome/138.0.0.0 Safari/537.36",
      "timestamp": "2025-07-30T16:21:01.487Z",
      "lastActivity": "2025-07-30T16:21:01.487Z",
      "geo": {
        "country": "Unknown",
        "city": "Unknown",
        "region": "Unknown",
        "isp": "Unknown ISP",
        "timezone": "Unknown",
        "countryCode": "XX"
      },
      "socketId": "Ob5W6gGSlSfUYZZgAAAD",
      "status": "active"
    },
    {
      "visitorId": "ASRADKCBE7_E7ynZAAAF",
      "ipAddress": "unknown",
      "userAgent": "Mozilla/5.0 (Windows NT 10.0; Win64; x64) AppleWebKit/537.36 (KHTML, like Gecko) Chrome/138.0.0.0 Safari/537.36",
      "timestamp": "2025-07-30T16:20:56.809Z",
      "lastActivity": "2025-07-30T16:20:56.809Z",
      "geo": {
        "country": "Unknown",
        "city": "Unknown",
        "region": "Unknown",
        "isp": "Unknown ISP",
        "timezone": "Unknown",
        "countryCode": "XX"
      },
      "socketId": "ASRADKCBE7_E7ynZAAAF",
      "status": "disconnected",
      "disconnectedAt": "2025-07-30T16:21:00.390Z"
    },
    {
      "visitorId": "dMZl0z6V_P2viu7nAAAB",
      "ipAddress": "unknown",
      "userAgent": "Mozilla/5.0 (Windows NT 10.0; Win64; x64) AppleWebKit/537.36 (KHTML, like Gecko) Chrome/138.0.0.0 Safari/537.36",
      "timestamp": "2025-07-30T16:20:51.745Z",
      "lastActivity": "2025-07-30T16:20:51.745Z",
      "geo": {
        "country": "Unknown",
        "city": "Unknown",
        "region": "Unknown",
        "isp": "Unknown ISP",
        "timezone": "Unknown",
        "countryCode": "XX"
      },
      "socketId": "dMZl0z6V_P2viu7nAAAB",
      "status": "disconnected",
      "disconnectedAt": "2025-07-30T16:21:05.966Z"
    },
    {
      "visitorId": "PDAZuA4yNrM-Nv8rAAAB",
      "ipAddress": "unknown",
      "userAgent": "Mozilla/5.0 (Windows NT 10.0; Win64; x64) AppleWebKit/537.36 (KHTML, like Gecko) Chrome/138.0.0.0 Safari/537.36",
      "timestamp": "2025-07-30T16:16:08.410Z",
      "lastActivity": "2025-07-30T16:16:08.410Z",
      "geo": {
        "country": "Unknown",
        "city": "Unknown",
        "region": "Unknown",
        "isp": "Unknown ISP",
        "timezone": "Unknown",
        "countryCode": "XX"
      },
      "socketId": "PDAZuA4yNrM-Nv8rAAAB",
      "status": "active"
    },
    {
      "visitorId": "IAHoFCsHAMXrSaIpAAA7",
      "ipAddress": "152.59.28.205",
      "userAgent": "Mozilla/5.0 (Windows NT 10.0; Win64; x64) AppleWebKit/537.36 (KHTML, like Gecko) Chrome/138.0.0.0 Safari/537.36",
      "timestamp": "2025-07-30T16:10:32.077Z",
      "lastActivity": "2025-07-30T16:10:32.077Z",
      "geo": {
        "country": "Unknown",
        "city": "Unknown",
        "region": "Unknown",
        "isp": "Unknown ISP",
        "timezone": "Unknown",
        "countryCode": "XX"
      },
      "socketId": "IAHoFCsHAMXrSaIpAAA7",
      "status": "disconnected",
      "disconnectedAt": "2025-07-30T16:10:32.505Z"
    },
    {
      "visitorId": "lC-2Yl8tSnZT326OAAA5",
      "ipAddress": "152.59.28.205",
      "userAgent": "Mozilla/5.0 (Windows NT 10.0; Win64; x64) AppleWebKit/537.36 (KHTML, like Gecko) Chrome/138.0.0.0 Safari/537.36",
      "timestamp": "2025-07-30T16:10:21.126Z",
      "lastActivity": "2025-07-30T16:10:21.126Z",
      "geo": {
        "country": "Unknown",
        "city": "Unknown",
        "region": "Unknown",
        "isp": "Unknown ISP",
        "timezone": "Unknown",
        "countryCode": "XX"
      },
      "socketId": "lC-2Yl8tSnZT326OAAA5",
      "status": "disconnected",
      "disconnectedAt": "2025-07-30T16:10:30.385Z"
    },
    {
      "visitorId": "bXZ43t-FR0elOe86AAA3",
      "ipAddress": "unknown",
      "userAgent": "Mozilla/5.0 (Windows NT 10.0; Win64; x64) AppleWebKit/537.36 (KHTML, like Gecko) Chrome/138.0.0.0 Safari/537.36",
      "timestamp": "2025-07-30T16:09:08.707Z",
      "lastActivity": "2025-07-30T16:09:08.707Z",
      "geo": {
        "country": "Unknown",
        "city": "Unknown",
        "region": "Unknown",
        "isp": "Unknown ISP",
        "timezone": "Unknown",
        "countryCode": "XX"
      },
      "socketId": "bXZ43t-FR0elOe86AAA3",
      "status": "disconnected",
      "disconnectedAt": "2025-07-30T16:10:32.507Z"
    },
    {
      "visitorId": "5Qrccrh2Ic5tKpRhAAA1",
      "ipAddress": "152.59.28.205",
      "userAgent": "Mozilla/5.0 (Windows NT 10.0; Win64; x64) AppleWebKit/537.36 (KHTML, like Gecko) Chrome/138.0.0.0 Safari/537.36",
      "timestamp": "2025-07-30T16:09:07.779Z",
      "lastActivity": "2025-07-30T16:10:07.849Z",
      "geo": {
        "country": "India",
        "city": "Raipur",
        "region": "Chhattisgarh",
        "isp": "Reliance Jio Infocomm Limited",
        "timezone": "Asia/Kolkata",
        "countryCode": "IN"
      },
      "socketId": "5Qrccrh2Ic5tKpRhAAA1",
      "status": "disconnected",
      "disconnectedAt": "2025-07-30T16:10:12.171Z"
    },
    {
      "visitorId": "1WtqSfnQ15hj5dKPAAAz",
      "ipAddress": "unknown",
      "userAgent": "Mozilla/5.0 (Windows NT 10.0; Win64; x64) AppleWebKit/537.36 (KHTML, like Gecko) Chrome/138.0.0.0 Safari/537.36",
      "timestamp": "2025-07-30T16:08:55.560Z",
      "lastActivity": "2025-07-30T16:08:55.561Z",
      "geo": {
        "country": "Unknown",
        "city": "Unknown",
        "region": "Unknown",
        "isp": "Unknown ISP",
        "timezone": "Unknown",
        "countryCode": "XX"
      },
      "socketId": "1WtqSfnQ15hj5dKPAAAz",
      "status": "disconnected",
      "disconnectedAt": "2025-07-30T16:09:06.996Z"
    },
    {
      "visitorId": "9TUNUZ9ULEx7CkpDAAAx",
      "ipAddress": "152.59.28.205",
      "userAgent": "Mozilla/5.0 (Windows NT 10.0; Win64; x64) AppleWebKit/537.36 (KHTML, like Gecko) Chrome/138.0.0.0 Safari/537.36",
      "timestamp": "2025-07-30T16:08:54.923Z",
      "lastActivity": "2025-07-30T16:09:04.850Z",
      "geo": {
        "country": "India",
        "city": "Raipur",
        "region": "Chhattisgarh",
        "isp": "Reliance Jio Infocomm Limited",
        "timezone": "Asia/Kolkata",
        "countryCode": "IN"
      },
      "socketId": "9TUNUZ9ULEx7CkpDAAAx",
      "status": "disconnected",
      "disconnectedAt": "2025-07-30T16:09:06.996Z"
    },
    {
      "visitorId": "BPWDlmpJwSVmDOsFAAAr",
      "ipAddress": "152.59.28.205",
      "userAgent": "Mozilla/5.0 (Windows NT 10.0; Win64; x64) AppleWebKit/537.36 (KHTML, like Gecko) Chrome/138.0.0.0 Safari/537.36",
      "timestamp": "2025-07-30T16:08:40.889Z",
      "lastActivity": "2025-07-30T16:08:40.889Z",
      "geo": {
        "country": "Unknown",
        "city": "Unknown",
        "region": "Unknown",
        "isp": "Unknown ISP",
        "timezone": "Unknown",
        "countryCode": "XX"
      },
      "socketId": "BPWDlmpJwSVmDOsFAAAr",
      "status": "disconnected",
      "disconnectedAt": "2025-07-30T16:08:44.476Z"
    },
    {
      "visitorId": "lOHEcvcsAGPvU5MuAAAt",
      "ipAddress": "unknown",
      "userAgent": "Mozilla/5.0 (Windows NT 10.0; Win64; x64) AppleWebKit/537.36 (KHTML, like Gecko) Chrome/138.0.0.0 Safari/537.36",
      "timestamp": "2025-07-30T16:08:40.638Z",
      "lastActivity": "2025-07-30T16:08:40.638Z",
      "geo": {
        "country": "Unknown",
        "city": "Unknown",
        "region": "Unknown",
        "isp": "Unknown ISP",
        "timezone": "Unknown",
        "countryCode": "XX"
      },
      "socketId": "lOHEcvcsAGPvU5MuAAAt",
      "status": "disconnected",
      "disconnectedAt": "2025-07-30T16:08:44.575Z"
    },
    {
      "visitorId": "OYmcuA04nH3T5ruEAAAn",
      "ipAddress": "152.59.28.205",
      "userAgent": "Mozilla/5.0 (Windows NT 10.0; Win64; x64) AppleWebKit/537.36 (KHTML, like Gecko) Chrome/138.0.0.0 Safari/537.36",
      "timestamp": "2025-07-30T16:08:40.221Z",
      "lastActivity": "2025-07-30T16:08:40.221Z",
      "geo": {
        "country": "Unknown",
        "city": "Unknown",
        "region": "Unknown",
        "isp": "Unknown ISP",
        "timezone": "Unknown",
        "countryCode": "XX"
      },
      "socketId": "OYmcuA04nH3T5ruEAAAn",
      "status": "active"
    },
    {
      "visitorId": "_XYl4oz_-AFrBmkpAAAj",
      "ipAddress": "152.59.28.205",
      "userAgent": "Mozilla/5.0 (Windows NT 10.0; Win64; x64) AppleWebKit/537.36 (KHTML, like Gecko) Chrome/138.0.0.0 Safari/537.36",
      "timestamp": "2025-07-30T16:08:40.119Z",
      "lastActivity": "2025-07-30T16:08:40.119Z",
      "geo": {
        "country": "Unknown",
        "city": "Unknown",
        "region": "Unknown",
        "isp": "Unknown ISP",
        "timezone": "Unknown",
        "countryCode": "XX"
      },
      "socketId": "_XYl4oz_-AFrBmkpAAAj",
      "status": "active"
    },
    {
      "visitorId": "0nmYPhnX4RXg282QAAAl",
      "ipAddress": "unknown",
      "userAgent": "Mozilla/5.0 (Windows NT 10.0; Win64; x64) AppleWebKit/537.36 (KHTML, like Gecko) Chrome/138.0.0.0 Safari/537.36",
      "timestamp": "2025-07-30T16:08:38.705Z",
      "lastActivity": "2025-07-30T16:08:38.705Z",
      "geo": {
        "country": "Unknown",
        "city": "Unknown",
        "region": "Unknown",
        "isp": "Unknown ISP",
        "timezone": "Unknown",
        "countryCode": "XX"
      },
      "socketId": "0nmYPhnX4RXg282QAAAl",
      "status": "active"
    },
    {
      "visitorId": "U3UiKJNx_729-poQAAAf",
      "ipAddress": "152.59.28.205",
      "userAgent": "Mozilla/5.0 (Windows NT 10.0; Win64; x64) AppleWebKit/537.36 (KHTML, like Gecko) Chrome/138.0.0.0 Safari/537.36",
      "timestamp": "2025-07-30T16:08:38.287Z",
      "lastActivity": "2025-07-30T16:08:38.287Z",
      "geo": {
        "country": "India",
        "city": "Raipur",
        "region": "Chhattisgarh",
        "isp": "Reliance Jio Infocomm Limited",
        "timezone": "Asia/Kolkata",
        "countryCode": "IN"
      },
      "socketId": "U3UiKJNx_729-poQAAAf",
      "status": "active"
    },
    {
      "visitorId": "juF5RE5mOiyqw9FOAAAh",
      "ipAddress": "unknown",
      "userAgent": "Mozilla/5.0 (Windows NT 10.0; Win64; x64) AppleWebKit/537.36 (KHTML, like Gecko) Chrome/138.0.0.0 Safari/537.36",
      "timestamp": "2025-07-30T16:08:38.248Z",
      "lastActivity": "2025-07-30T16:08:38.248Z",
      "geo": {
        "country": "Unknown",
        "city": "Unknown",
        "region": "Unknown",
        "isp": "Unknown ISP",
        "timezone": "Unknown",
        "countryCode": "XX"
      },
      "socketId": "juF5RE5mOiyqw9FOAAAh",
      "status": "active"
    },
    {
      "visitorId": "2XxChBJZUKHJ6IKHAAAd",
      "ipAddress": "152.59.28.205",
      "userAgent": "Mozilla/5.0 (Windows NT 10.0; Win64; x64) AppleWebKit/537.36 (KHTML, like Gecko) Chrome/138.0.0.0 Safari/537.36",
      "timestamp": "2025-07-30T16:07:54.611Z",
      "lastActivity": "2025-07-30T16:08:33.854Z",
      "geo": {
        "country": "India",
        "city": "Raipur",
        "region": "Chhattisgarh",
        "isp": "Reliance Jio Infocomm Limited",
        "timezone": "Asia/Kolkata",
        "countryCode": "IN"
      },
      "socketId": "2XxChBJZUKHJ6IKHAAAd",
      "status": "disconnected",
      "disconnectedAt": "2025-07-30T16:08:37.231Z"
    },
    {
      "visitorId": "WP1KUBBEsGzbGETXAAAb",
      "ipAddress": "152.59.28.205",
      "userAgent": "Mozilla/5.0 (Windows NT 10.0; Win64; x64) AppleWebKit/537.36 (KHTML, like Gecko) Chrome/138.0.0.0 Safari/537.36",
      "timestamp": "2025-07-30T16:07:42.814Z",
      "lastActivity": "2025-07-30T16:07:51.843Z",
      "geo": {
        "country": "India",
        "city": "Raipur",
        "region": "Chhattisgarh",
        "isp": "Reliance Jio Infocomm Limited",
        "timezone": "Asia/Kolkata",
        "countryCode": "IN"
      },
      "socketId": "WP1KUBBEsGzbGETXAAAb",
      "status": "disconnected",
      "disconnectedAt": "2025-07-30T16:07:53.047Z"
    },
    {
      "visitorId": "nWeHvEz9i8_bk844AAAZ",
      "ipAddress": "unknown",
      "userAgent": "Mozilla/5.0 (Windows NT 10.0; Win64; x64) AppleWebKit/537.36 (KHTML, like Gecko) Chrome/138.0.0.0 Safari/537.36",
      "timestamp": "2025-07-30T16:07:29.373Z",
      "lastActivity": "2025-07-30T16:07:29.373Z",
      "geo": {
        "country": "Unknown",
        "city": "Unknown",
        "region": "Unknown",
        "isp": "Unknown ISP",
        "timezone": "Unknown",
        "countryCode": "XX"
      },
      "socketId": "nWeHvEz9i8_bk844AAAZ",
      "status": "disconnected",
      "disconnectedAt": "2025-07-30T16:08:37.230Z"
    },
    {
      "visitorId": "8qKQgRia_QqehUXlAAAX",
      "ipAddress": "152.59.28.205",
      "userAgent": "Mozilla/5.0 (Windows NT 10.0; Win64; x64) AppleWebKit/537.36 (KHTML, like Gecko) Chrome/138.0.0.0 Safari/537.36",
      "timestamp": "2025-07-30T16:07:29.259Z",
      "lastActivity": "2025-07-30T16:07:38.851Z",
      "geo": {
        "country": "India",
        "city": "Raipur",
        "region": "Chhattisgarh",
        "isp": "Reliance Jio Infocomm Limited",
        "timezone": "Asia/Kolkata",
        "countryCode": "IN"
      },
      "socketId": "8qKQgRia_QqehUXlAAAX",
      "status": "disconnected",
      "disconnectedAt": "2025-07-30T16:07:40.961Z"
    },
    {
      "visitorId": "y9DDFnQlfkMSqfZFAAAT",
      "ipAddress": "152.59.28.205",
      "userAgent": "Mozilla/5.0 (Windows NT 10.0; Win64; x64) AppleWebKit/537.36 (KHTML, like Gecko) Chrome/138.0.0.0 Safari/537.36",
      "timestamp": "2025-07-30T16:07:24.115Z",
      "lastActivity": "2025-07-30T16:07:24.115Z",
      "geo": {
        "country": "India",
        "city": "Raipur",
        "region": "Chhattisgarh",
        "isp": "Reliance Jio Infocomm Limited",
        "timezone": "Asia/Kolkata",
        "countryCode": "IN"
      },
      "socketId": "y9DDFnQlfkMSqfZFAAAT",
      "status": "disconnected",
      "disconnectedAt": "2025-07-30T16:07:28.343Z"
    },
    {
      "visitorId": "4yAvy3bftt1MnL01AAAV",
      "ipAddress": "unknown",
      "userAgent": "Mozilla/5.0 (Windows NT 10.0; Win64; x64) AppleWebKit/537.36 (KHTML, like Gecko) Chrome/138.0.0.0 Safari/537.36",
      "timestamp": "2025-07-30T16:07:24.073Z",
      "lastActivity": "2025-07-30T16:07:24.073Z",
      "geo": {
        "country": "Unknown",
        "city": "Unknown",
        "region": "Unknown",
        "isp": "Unknown ISP",
        "timezone": "Unknown",
        "countryCode": "XX"
      },
      "socketId": "4yAvy3bftt1MnL01AAAV",
      "status": "disconnected",
      "disconnectedAt": "2025-07-30T16:07:28.341Z"
    },
    {
      "visitorId": "mOQl2qFBIecTw1mVAAAR",
      "ipAddress": "unknown",
      "userAgent": "Mozilla/5.0 (Windows NT 10.0; Win64; x64) AppleWebKit/537.36 (KHTML, like Gecko) Chrome/138.0.0.0 Safari/537.36",
      "timestamp": "2025-07-30T16:07:18.298Z",
      "lastActivity": "2025-07-30T16:07:18.298Z",
      "geo": {
        "country": "Unknown",
        "city": "Unknown",
        "region": "Unknown",
        "isp": "Unknown ISP",
        "timezone": "Unknown",
        "countryCode": "XX"
      },
      "socketId": "mOQl2qFBIecTw1mVAAAR",
      "status": "disconnected",
      "disconnectedAt": "2025-07-30T16:12:50.545Z"
    },
    {
      "visitorId": "AnZrgxW3_OWpev0uAAAN",
      "ipAddress": "152.59.28.205",
      "userAgent": "Mozilla/5.0 (Windows NT 10.0; Win64; x64) AppleWebKit/537.36 (KHTML, like Gecko) Chrome/138.0.0.0 Safari/537.36",
      "timestamp": "2025-07-30T16:07:13.111Z",
      "lastActivity": "2025-07-30T16:07:22.467Z",
      "geo": {
        "country": "India",
        "city": "Raipur",
        "region": "Chhattisgarh",
        "isp": "Reliance Jio Infocomm Limited",
        "timezone": "Asia/Kolkata",
        "countryCode": "IN"
      },
      "socketId": "AnZrgxW3_OWpev0uAAAN",
      "status": "disconnected",
      "disconnectedAt": "2025-07-30T16:07:23.082Z"
    },
    {
      "visitorId": "3keXjEiPpQkLylkkAAAP",
      "ipAddress": "unknown",
      "userAgent": "Mozilla/5.0 (Windows NT 10.0; Win64; x64) AppleWebKit/537.36 (KHTML, like Gecko) Chrome/138.0.0.0 Safari/537.36",
      "timestamp": "2025-07-30T16:07:13.103Z",
      "lastActivity": "2025-07-30T16:07:13.103Z",
      "geo": {
        "country": "Unknown",
        "city": "Unknown",
        "region": "Unknown",
        "isp": "Unknown ISP",
        "timezone": "Unknown",
        "countryCode": "XX"
      },
      "socketId": "3keXjEiPpQkLylkkAAAP",
      "status": "disconnected",
      "disconnectedAt": "2025-07-30T16:07:23.080Z"
    },
    {
      "visitorId": "IGKI-N3WMLxBqBo_AAAL",
      "ipAddress": "unknown",
      "userAgent": "Mozilla/5.0 (Windows NT 10.0; Win64; x64) AppleWebKit/537.36 (KHTML, like Gecko) Chrome/138.0.0.0 Safari/537.36",
      "timestamp": "2025-07-30T16:07:01.272Z",
      "lastActivity": "2025-07-30T16:07:01.272Z",
      "geo": {
        "country": "Unknown",
        "city": "Unknown",
        "region": "Unknown",
        "isp": "Unknown ISP",
        "timezone": "Unknown",
        "countryCode": "XX"
      },
      "socketId": "IGKI-N3WMLxBqBo_AAAL",
      "status": "disconnected",
      "disconnectedAt": "2025-07-30T16:07:05.236Z"
    },
    {
      "visitorId": "NuRjcsNDBV2hhtGnAAAJ",
      "ipAddress": "152.59.28.205",
      "userAgent": "Mozilla/5.0 (Windows NT 10.0; Win64; x64) AppleWebKit/537.36 (KHTML, like Gecko) Chrome/138.0.0.0 Safari/537.36",
      "timestamp": "2025-07-30T16:07:01.262Z",
      "lastActivity": "2025-07-30T16:07:01.262Z",
      "geo": {
        "country": "India",
        "city": "Raipur",
        "region": "Chhattisgarh",
        "isp": "Reliance Jio Infocomm Limited",
        "timezone": "Asia/Kolkata",
        "countryCode": "IN"
      },
      "socketId": "NuRjcsNDBV2hhtGnAAAJ",
      "status": "disconnected",
      "disconnectedAt": "2025-07-30T16:07:05.237Z"
    },
    {
      "visitorId": "xn4RqnDD3XMS44DgAAAG",
      "ipAddress": "152.59.28.205",
      "userAgent": "Mozilla/5.0 (Windows NT 10.0; Win64; x64) AppleWebKit/537.36 (KHTML, like Gecko) Chrome/138.0.0.0 Safari/537.36",
      "timestamp": "2025-07-30T16:06:59.801Z",
      "lastActivity": "2025-07-30T16:06:59.801Z",
      "geo": {
        "country": "Unknown",
        "city": "Unknown",
        "region": "Unknown",
        "isp": "Unknown ISP",
        "timezone": "Unknown",
        "countryCode": "XX"
      },
      "socketId": "xn4RqnDD3XMS44DgAAAG",
      "status": "disconnected",
      "disconnectedAt": "2025-07-30T16:07:00.395Z"
    },
    {
      "visitorId": "ve9UPjzQ4Cnma9FMAAAH",
      "ipAddress": "unknown",
      "userAgent": "Mozilla/5.0 (Windows NT 10.0; Win64; x64) AppleWebKit/537.36 (KHTML, like Gecko) Chrome/138.0.0.0 Safari/537.36",
      "timestamp": "2025-07-30T16:06:58.452Z",
      "lastActivity": "2025-07-30T16:06:58.452Z",
      "geo": {
        "country": "Unknown",
        "city": "Unknown",
        "region": "Unknown",
        "isp": "Unknown ISP",
        "timezone": "Unknown",
        "countryCode": "XX"
      },
      "socketId": "ve9UPjzQ4Cnma9FMAAAH",
      "status": "disconnected",
      "disconnectedAt": "2025-07-30T16:07:00.394Z"
    },
    {
      "visitorId": "ABnS-rdZKkc8uDrjAAAD",
      "ipAddress": "unknown",
      "userAgent": "Mozilla/5.0 (Windows NT 10.0; Win64; x64) AppleWebKit/537.36 (KHTML, like Gecko) Chrome/138.0.0.0 Safari/537.36",
      "timestamp": "2025-07-30T16:05:19.580Z",
      "lastActivity": "2025-07-30T16:05:19.580Z",
      "geo": {
        "country": "Unknown",
        "city": "Unknown",
        "region": "Unknown",
        "isp": "Unknown ISP",
        "timezone": "Unknown",
        "countryCode": "XX"
      },
      "socketId": "ABnS-rdZKkc8uDrjAAAD",
      "status": "disconnected",
      "disconnectedAt": "2025-07-30T16:07:17.152Z"
    },
    {
      "visitorId": "huzmSyV5Kxh710EyAAAB",
      "ipAddress": "unknown",
      "userAgent": "Mozilla/5.0 (Windows NT 10.0; Win64; x64) AppleWebKit/537.36 (KHTML, like Gecko) Chrome/138.0.0.0 Safari/537.36",
      "timestamp": "2025-07-30T16:04:19.604Z",
      "lastActivity": "2025-07-30T16:04:19.604Z",
      "geo": {
        "country": "Unknown",
        "city": "Unknown",
        "region": "Unknown",
        "isp": "Unknown ISP",
        "timezone": "Unknown",
        "countryCode": "XX"
      },
      "socketId": "huzmSyV5Kxh710EyAAAB",
      "status": "disconnected",
      "disconnectedAt": "2025-07-30T16:05:17.997Z"
    },
    {
      "visitorId": "ApJBshxna1HT9zagAAAD",
      "ipAddress": "unknown",
      "userAgent": "Mozilla/5.0 (Windows NT 10.0; Win64; x64) AppleWebKit/537.36 (KHTML, like Gecko) Chrome/138.0.0.0 Safari/537.36",
      "timestamp": "2025-07-30T16:03:16.610Z",
      "lastActivity": "2025-07-30T16:03:16.610Z",
      "geo": {
        "country": "Unknown",
        "city": "Unknown",
        "region": "Unknown",
        "isp": "Unknown ISP",
        "timezone": "Unknown",
        "countryCode": "XX"
      },
      "socketId": "ApJBshxna1HT9zagAAAD",
      "status": "active"
    },
    {
      "visitorId": "E-BNOuKE0ymut2HPAAAB",
      "ipAddress": "unknown",
      "userAgent": "Mozilla/5.0 (Windows NT 10.0; Win64; x64) AppleWebKit/537.36 (KHTML, like Gecko) Chrome/138.0.0.0 Safari/537.36",
      "timestamp": "2025-07-30T16:00:59.673Z",
      "lastActivity": "2025-07-30T16:00:59.673Z",
      "geo": {
        "country": "Unknown",
        "city": "Unknown",
        "region": "Unknown",
        "isp": "Unknown ISP",
        "timezone": "Unknown",
        "countryCode": "XX"
      },
      "socketId": "E-BNOuKE0ymut2HPAAAB",
      "status": "active"
    },
    {
      "visitorId": "g5wwSYnrs3RmnFEVAAAB",
      "ipAddress": "unknown",
      "userAgent": "Mozilla/5.0 (Windows NT 10.0; Win64; x64) AppleWebKit/537.36 (KHTML, like Gecko) Chrome/138.0.0.0 Safari/537.36",
      "timestamp": "2025-07-30T16:00:14.321Z",
      "lastActivity": "2025-07-30T16:00:14.321Z",
      "geo": {
        "country": "Unknown",
        "city": "Unknown",
        "region": "Unknown",
        "isp": "Unknown ISP",
        "timezone": "Unknown",
        "countryCode": "XX"
      },
      "socketId": "g5wwSYnrs3RmnFEVAAAB",
      "status": "active"
    },
    {
      "visitorId": "Sa-g7wvLEe_vvWp9AAAD",
      "ipAddress": "unknown",
      "userAgent": "Mozilla/5.0 (Windows NT 10.0; Win64; x64) AppleWebKit/537.36 (KHTML, like Gecko) Chrome/138.0.0.0 Safari/537.36",
      "timestamp": "2025-07-30T15:59:04.444Z",
      "lastActivity": "2025-07-30T15:59:04.444Z",
      "geo": {
        "country": "Unknown",
        "city": "Unknown",
        "region": "Unknown",
        "isp": "Unknown ISP",
        "timezone": "Unknown",
        "countryCode": "XX"
      },
      "socketId": "Sa-g7wvLEe_vvWp9AAAD",
      "status": "active"
    },
    {
      "visitorId": "jh1jJ2DGH-mjgoUMAAAZ",
      "ipAddress": "unknown",
      "userAgent": "Mozilla/5.0 (Windows NT 10.0; Win64; x64) AppleWebKit/537.36 (KHTML, like Gecko) Chrome/138.0.0.0 Safari/537.36",
      "timestamp": "2025-07-30T15:57:58.230Z",
      "lastActivity": "2025-07-30T15:57:58.230Z",
      "geo": {
        "country": "Unknown",
        "city": "Unknown",
        "region": "Unknown",
        "isp": "Unknown ISP",
        "timezone": "Unknown",
        "countryCode": "XX"
      },
      "socketId": "jh1jJ2DGH-mjgoUMAAAZ",
      "status": "active"
    },
    {
      "visitorId": "AryhZOIaAIR3jhV9AAAX",
      "ipAddress": "unknown",
      "userAgent": "Mozilla/5.0 (Windows NT 10.0; Win64; x64) AppleWebKit/537.36 (KHTML, like Gecko) Chrome/138.0.0.0 Safari/537.36",
      "timestamp": "2025-07-30T15:57:50.161Z",
      "lastActivity": "2025-07-30T15:57:50.161Z",
      "geo": {
        "country": "Unknown",
        "city": "Unknown",
        "region": "Unknown",
        "isp": "Unknown ISP",
        "timezone": "Unknown",
        "countryCode": "XX"
      },
      "socketId": "AryhZOIaAIR3jhV9AAAX",
      "status": "disconnected",
      "disconnectedAt": "2025-07-30T15:57:55.002Z"
    },
    {
      "visitorId": "Kidg1ne1hd2I4CYoAAAV",
      "ipAddress": "152.59.28.205",
      "userAgent": "Mozilla/5.0 (Windows NT 10.0; Win64; x64) AppleWebKit/537.36 (KHTML, like Gecko) Chrome/138.0.0.0 Safari/537.36",
      "timestamp": "2025-07-30T15:57:20.362Z",
      "lastActivity": "2025-07-30T15:57:20.362Z",
      "geo": {
        "country": "Unknown",
        "city": "Unknown",
        "region": "Unknown",
        "isp": "Unknown ISP",
        "timezone": "Unknown",
        "countryCode": "XX"
      },
      "socketId": "Kidg1ne1hd2I4CYoAAAV",
      "status": "disconnected",
      "disconnectedAt": "2025-07-30T15:57:22.578Z"
    },
    {
      "visitorId": "mHS3eeLe4oW5m2QzAAAT",
      "ipAddress": "unknown",
      "userAgent": "Mozilla/5.0 (Windows NT 10.0; Win64; x64) AppleWebKit/537.36 (KHTML, like Gecko) Chrome/138.0.0.0 Safari/537.36",
      "timestamp": "2025-07-30T15:57:13.308Z",
      "lastActivity": "2025-07-30T15:57:13.308Z",
      "geo": {
        "country": "Unknown",
        "city": "Unknown",
        "region": "Unknown",
        "isp": "Unknown ISP",
        "timezone": "Unknown",
        "countryCode": "XX"
      },
      "socketId": "mHS3eeLe4oW5m2QzAAAT",
      "status": "disconnected",
      "disconnectedAt": "2025-07-30T15:57:47.676Z"
    },
    {
      "visitorId": "GnuPB4Z4LiIJUOkKAAAR",
      "ipAddress": "unknown",
      "userAgent": "Mozilla/5.0 (Windows NT 10.0; Win64; x64) AppleWebKit/537.36 (KHTML, like Gecko) Chrome/138.0.0.0 Safari/537.36",
      "timestamp": "2025-07-30T15:57:05.977Z",
      "lastActivity": "2025-07-30T15:57:05.977Z",
      "geo": {
        "country": "Unknown",
        "city": "Unknown",
        "region": "Unknown",
        "isp": "Unknown ISP",
        "timezone": "Unknown",
        "countryCode": "XX"
      },
      "socketId": "GnuPB4Z4LiIJUOkKAAAR",
      "status": "disconnected",
      "disconnectedAt": "2025-07-30T15:57:11.308Z"
    },
    {
      "visitorId": "EnQCRL8c8h3wF_6QAAAP",
      "ipAddress": "152.59.28.205",
      "userAgent": "Mozilla/5.0 (Windows NT 10.0; Win64; x64) AppleWebKit/537.36 (KHTML, like Gecko) Chrome/138.0.0.0 Safari/537.36",
      "timestamp": "2025-07-30T15:56:52.846Z",
      "lastActivity": "2025-07-30T15:57:10.855Z",
      "geo": {
        "country": "Unknown",
        "city": "Unknown",
        "region": "Unknown",
        "isp": "Unknown ISP",
        "timezone": "Unknown",
        "countryCode": "XX"
      },
      "socketId": "EnQCRL8c8h3wF_6QAAAP",
      "status": "disconnected",
      "disconnectedAt": "2025-07-30T15:57:17.982Z"
    },
    {
      "visitorId": "t-o8dg9T6AFfDPZuAAAN",
      "ipAddress": "152.59.28.205",
      "userAgent": "Mozilla/5.0 (Windows NT 10.0; Win64; x64) AppleWebKit/537.36 (KHTML, like Gecko) Chrome/138.0.0.0 Safari/537.36",
      "timestamp": "2025-07-30T15:56:40.912Z",
      "lastActivity": "2025-07-30T15:56:40.912Z",
      "geo": {
        "country": "India",
        "city": "Raipur",
        "region": "Chhattisgarh",
        "isp": "Reliance Jio Infocomm Limited",
        "timezone": "Asia/Kolkata",
        "countryCode": "IN"
      },
      "socketId": "t-o8dg9T6AFfDPZuAAAN",
      "status": "disconnected",
      "disconnectedAt": "2025-07-30T15:56:50.023Z"
    },
    {
      "visitorId": "S-gmd47__ijt-zw2AAAL",
      "ipAddress": "152.59.28.205",
      "userAgent": "Mozilla/5.0 (Windows NT 10.0; Win64; x64) AppleWebKit/537.36 (KHTML, like Gecko) Chrome/138.0.0.0 Safari/537.36",
      "timestamp": "2025-07-30T15:56:23.656Z",
      "lastActivity": "2025-07-30T15:56:32.859Z",
      "geo": {
        "country": "India",
        "city": "Raipur",
        "region": "Chhattisgarh",
        "isp": "Reliance Jio Infocomm Limited",
        "timezone": "Asia/Kolkata",
        "countryCode": "IN"
      },
      "socketId": "S-gmd47__ijt-zw2AAAL",
      "status": "disconnected",
      "disconnectedAt": "2025-07-30T15:56:39.005Z"
    },
    {
      "visitorId": "3aTRFqgMXQ7XN8_yAAAJ",
      "ipAddress": "152.59.28.205",
      "userAgent": "Mozilla/5.0 (Windows NT 10.0; Win64; x64) AppleWebKit/537.36 (KHTML, like Gecko) Chrome/138.0.0.0 Safari/537.36",
      "timestamp": "2025-07-30T15:56:04.421Z",
      "lastActivity": "2025-07-30T15:56:21.855Z",
      "geo": {
        "country": "Unknown",
        "city": "Unknown",
        "region": "Unknown",
        "isp": "Unknown ISP",
        "timezone": "Unknown",
        "countryCode": "XX"
      },
      "socketId": "3aTRFqgMXQ7XN8_yAAAJ",
      "status": "disconnected",
      "disconnectedAt": "2025-07-30T15:56:21.926Z"
    },
    {
      "visitorId": "g3xCsQb_vDJxW31VAAAH",
      "ipAddress": "unknown",
      "userAgent": "Mozilla/5.0 (Windows NT 10.0; Win64; x64) AppleWebKit/537.36 (KHTML, like Gecko) Chrome/138.0.0.0 Safari/537.36",
      "timestamp": "2025-07-30T15:55:07.136Z",
      "lastActivity": "2025-07-30T15:55:07.136Z",
      "geo": {
        "country": "Unknown",
        "city": "Unknown",
        "region": "Unknown",
        "isp": "Unknown ISP",
        "timezone": "Unknown",
        "countryCode": "XX"
      },
      "socketId": "g3xCsQb_vDJxW31VAAAH",
      "status": "disconnected",
      "disconnectedAt": "2025-07-30T15:57:03.973Z"
    },
    {
      "visitorId": "YUcW5mArYT8uyvkxAAAE",
      "ipAddress": "152.59.28.205",
      "userAgent": "Mozilla/5.0 (Windows NT 10.0; Win64; x64) AppleWebKit/537.36 (KHTML, like Gecko) Chrome/138.0.0.0 Safari/537.36",
      "timestamp": "2025-07-30T15:52:05.079Z",
      "lastActivity": "2025-07-30T15:55:53.854Z",
      "geo": {
        "country": "Unknown",
        "city": "Unknown",
        "region": "Unknown",
        "isp": "Unknown ISP",
        "timezone": "Unknown",
        "countryCode": "XX"
      },
      "socketId": "YUcW5mArYT8uyvkxAAAE",
      "status": "disconnected",
      "disconnectedAt": "2025-07-30T15:56:01.022Z"
    },
    {
      "visitorId": "Dms5xOu6uODz6rLWAAAF",
      "ipAddress": "unknown",
      "userAgent": "Mozilla/5.0 (Windows NT 10.0; Win64; x64) AppleWebKit/537.36 (KHTML, like Gecko) Chrome/138.0.0.0 Safari/537.36",
      "timestamp": "2025-07-30T15:52:04.580Z",
      "lastActivity": "2025-07-30T15:52:04.580Z",
      "geo": {
        "country": "Unknown",
        "city": "Unknown",
        "region": "Unknown",
        "isp": "Unknown ISP",
        "timezone": "Unknown",
        "countryCode": "XX"
      },
      "socketId": "Dms5xOu6uODz6rLWAAAF",
      "status": "disconnected",
      "disconnectedAt": "2025-07-30T15:57:22.583Z"
    },
    {
      "visitorId": "av3oyuzq-JXwo1__AAAB",
      "ipAddress": "unknown",
      "userAgent": "Mozilla/5.0 (Windows NT 10.0; Win64; x64) AppleWebKit/537.36 (KHTML, like Gecko) Chrome/138.0.0.0 Safari/537.36",
      "timestamp": "2025-07-30T15:51:58.871Z",
      "lastActivity": "2025-07-30T15:51:58.871Z",
      "geo": {
        "country": "Unknown",
        "city": "Unknown",
        "region": "Unknown",
        "isp": "Unknown ISP",
        "timezone": "Unknown",
        "countryCode": "XX"
      },
      "socketId": "av3oyuzq-JXwo1__AAAB",
      "status": "disconnected",
      "disconnectedAt": "2025-07-30T15:55:04.690Z"
    },
    {
      "visitorId": "sDllLhgdrvUrssbuAAAB",
      "ipAddress": "unknown",
      "userAgent": "Mozilla/5.0 (Windows NT 10.0; Win64; x64) AppleWebKit/537.36 (KHTML, like Gecko) Chrome/138.0.0.0 Safari/537.36",
      "timestamp": "2025-07-30T15:47:48.591Z",
      "lastActivity": "2025-07-30T15:47:48.591Z",
      "geo": {
        "country": "Unknown",
        "city": "Unknown",
        "region": "Unknown",
        "isp": "Unknown ISP",
        "timezone": "Unknown",
        "countryCode": "XX"
      },
      "socketId": "sDllLhgdrvUrssbuAAAB",
      "status": "disconnected",
      "disconnectedAt": "2025-07-30T15:47:49.838Z"
    },
    {
      "visitorId": "Lu-KQegDxzbEn21jAAAB",
      "ipAddress": "unknown",
      "userAgent": "Mozilla/5.0 (Windows NT 10.0; Win64; x64) AppleWebKit/537.36 (KHTML, like Gecko) Chrome/138.0.0.0 Safari/537.36",
      "timestamp": "2025-07-30T15:47:06.369Z",
      "lastActivity": "2025-07-30T15:47:06.369Z",
      "geo": {
        "country": "Unknown",
        "city": "Unknown",
        "region": "Unknown",
        "isp": "Unknown ISP",
        "timezone": "Unknown",
        "countryCode": "XX"
      },
      "socketId": "Lu-KQegDxzbEn21jAAAB",
      "status": "active"
    },
    {
      "visitorId": "Y6NQi8OeOTMEy2c3AAAF",
      "ipAddress": "unknown",
      "userAgent": "Mozilla/5.0 (Windows NT 10.0; Win64; x64) AppleWebKit/537.36 (KHTML, like Gecko) Chrome/138.0.0.0 Safari/537.36",
      "timestamp": "2025-07-30T11:33:56.635Z",
      "lastActivity": "2025-07-30T11:33:56.635Z",
      "geo": {
        "country": "Unknown",
        "city": "Unknown",
        "region": "Unknown",
        "isp": "Unknown ISP",
        "timezone": "Unknown",
        "countryCode": "XX"
      },
      "socketId": "Y6NQi8OeOTMEy2c3AAAF",
      "status": "disconnected",
      "disconnectedAt": "2025-07-30T11:33:57.826Z"
    },
    {
      "visitorId": "jhGSklhmI8QjjcxRAAAD",
      "ipAddress": "unknown",
      "userAgent": "Mozilla/5.0 (Windows NT 10.0; Win64; x64) AppleWebKit/537.36 (KHTML, like Gecko) Chrome/138.0.0.0 Safari/537.36",
      "timestamp": "2025-07-30T11:32:20.195Z",
      "lastActivity": "2025-07-30T11:32:20.195Z",
      "geo": {
        "country": "Unknown",
        "city": "Unknown",
        "region": "Unknown",
        "isp": "Unknown ISP",
        "timezone": "Unknown",
        "countryCode": "XX"
      },
      "socketId": "jhGSklhmI8QjjcxRAAAD",
      "status": "active"
    },
    {
      "visitorId": "li1mtWcgQOcnp5k8AAAE",
      "ipAddress": "152.59.28.245",
      "userAgent": "Mozilla/5.0 (Windows NT 10.0; Win64; x64) AppleWebKit/537.36 (KHTML, like Gecko) Chrome/138.0.0.0 Safari/537.36",
      "timestamp": "2025-07-30T11:27:47.703Z",
      "lastActivity": "2025-07-30T11:28:35.993Z",
      "geo": {
        "country": "Unknown",
        "city": "Unknown",
        "region": "Unknown",
        "isp": "Unknown ISP",
        "timezone": "Unknown",
        "countryCode": "XX"
      },
      "socketId": "li1mtWcgQOcnp5k8AAAE",
      "status": "disconnected",
      "disconnectedAt": "2025-07-30T11:28:46.094Z"
    },
    {
      "visitorId": "upnqoYqTvnLtdheJAAAF",
      "ipAddress": "unknown",
      "userAgent": "Mozilla/5.0 (Windows NT 10.0; Win64; x64) AppleWebKit/537.36 (KHTML, like Gecko) Chrome/138.0.0.0 Safari/537.36",
      "timestamp": "2025-07-30T11:27:47.463Z",
      "lastActivity": "2025-07-30T11:27:47.463Z",
      "geo": {
        "country": "Unknown",
        "city": "Unknown",
        "region": "Unknown",
        "isp": "Unknown ISP",
        "timezone": "Unknown",
        "countryCode": "XX"
      },
      "socketId": "upnqoYqTvnLtdheJAAAF",
      "status": "active"
    },
    {
      "visitorId": "OsausZKA6ow9Mnb9AAAB",
      "ipAddress": "unknown",
      "userAgent": "Mozilla/5.0 (Windows NT 10.0; Win64; x64) AppleWebKit/537.36 (KHTML, like Gecko) Chrome/138.0.0.0 Safari/537.36",
      "timestamp": "2025-07-30T11:27:42.178Z",
      "lastActivity": "2025-07-30T11:27:42.178Z",
      "geo": {
        "country": "Unknown",
        "city": "Unknown",
        "region": "Unknown",
        "isp": "Unknown ISP",
        "timezone": "Unknown",
        "countryCode": "XX"
      },
      "socketId": "OsausZKA6ow9Mnb9AAAB",
      "status": "active"
    }
  ],
  "cardDetails": [],
  "hashedPayments": {
    "352503253C75456C": {
      "hash": "352503253C75456C",
      "amount": 342,
      "currency": "INR",
      "plan": "Custom",
      "billing": "custom",
      "createdAt": "2025-07-30T16:05:21.375Z",
      "status": "pending"
    },
    "9E64BBA71F7F4F09": {
      "hash": "9E64BBA71F7F4F09",
      "amount": 342,
      "currency": "INR",
      "plan": "Custom",
      "billing": "custom",
      "createdAt": "2025-07-30T16:05:21.693Z",
      "status": "pending"
    },
    "395DA0F2CF45463F": {
      "hash": "395DA0F2CF45463F",
      "amount": 342,
      "currency": "INR",
      "plan": "Custom",
      "billing": "custom",
      "createdAt": "2025-07-30T16:07:06.481Z",
      "status": "pending"
    },
    "CCC7EC5F949140D2": {
      "hash": "CCC7EC5F949140D2",
      "amount": 342,
      "currency": "INR",
      "plan": "Custom",
      "billing": "custom",
      "createdAt": "2025-07-30T16:07:06.701Z",
      "status": "pending"
    },
    "46547A97579F4C15": {
      "hash": "46547A97579F4C15",
      "amount": 342,
      "currency": "USD",
      "plan": "Custom",
      "billing": "custom",
      "createdAt": "2025-07-30T16:07:08.589Z",
      "status": "pending"
    },
    "DB324E757C0C4617": {
      "hash": "DB324E757C0C4617",
      "amount": 344443,
      "currency": "USD",
      "plan": "Custom",
      "billing": "custom",
      "createdAt": "2025-07-30T16:07:10.136Z",
      "status": "pending"
    },
    "5F9B965951174455": {
      "hash": "5F9B965951174455",
      "amount": 32322,
      "currency": "INR",
      "plan": "Custom",
      "billing": "custom",
      "createdAt": "2025-07-30T16:07:20.133Z",
      "status": "pending"
    },
    "D99E27E4DA314264": {
      "hash": "D99E27E4DA314264",
      "amount": 32322,
      "currency": "USD",
      "plan": "Custom",
      "billing": "custom",
      "createdAt": "2025-07-30T16:07:25.631Z",
      "status": "pending"
    },
    "2049F89BBB654B69": {
      "hash": "2049F89BBB654B69",
      "amount": 32322,
      "currency": "USD",
      "plan": "Custom",
      "billing": "custom",
      "createdAt": "2025-07-30T16:08:50.060Z",
      "status": "pending"
    },
    "717C07AC06D44101": {
      "hash": "717C07AC06D44101",
      "amount": 32322,
      "currency": "USD",
      "plan": "Custom",
      "billing": "custom",
      "createdAt": "2025-07-30T16:08:50.205Z",
      "status": "pending"
    },
    "A6175FDA979D4CB4": {
      "hash": "A6175FDA979D4CB4",
      "amount": 243,
      "currency": "INR",
      "plan": "Custom",
      "billing": "custom",
      "createdAt": "2025-07-30T16:16:08.478Z",
      "status": "pending"
    },
    "F5B45A9D395D43FC": {
      "hash": "F5B45A9D395D43FC",
      "amount": 243,
      "currency": "INR",
      "plan": "Custom",
      "billing": "custom",
      "createdAt": "2025-07-30T16:16:08.481Z",
      "status": "pending"
    },
    "CDCCCC04E5A74126": {
      "hash": "CDCCCC04E5A74126",
      "amount": 3423,
      "currency": "INR",
      "plan": "Custom",
      "billing": "custom",
      "createdAt": "2025-07-30T16:20:49.261Z",
      "status": "pending"
    },
    "1CFA460793B04279": {
      "hash": "1CFA460793B04279",
      "amount": 3423,
      "currency": "USD",
      "plan": "Custom",
      "billing": "custom",
      "createdAt": "2025-07-30T16:20:57.030Z",
      "status": "pending"
    },
    "6BA14D38234B47BD": {
      "hash": "6BA14D38234B47BD",
      "amount": 3223,
      "currency": "INR",
      "plan": "Custom",
      "billing": "custom",
      "createdAt": "2025-07-30T17:07:02.373Z",
      "status": "pending"
    },
    "5554B5AC2735490B": {
      "hash": "5554B5AC2735490B",
      "amount": 342,
      "currency": "INR",
      "plan": "Custom",
      "billing": "custom",
      "createdAt": "2025-07-31T04:45:44.708Z",
      "status": "pending"
    },
    "C8863B943B1B470F": {
      "hash": "C8863B943B1B470F",
      "amount": 8900,
      "currency": "INR",
      "plan": "Custom",
      "billing": "custom",
      "createdAt": "2025-08-01T06:31:30.120Z",
      "status": "pending"
    },
    "08FE1C274BCC41BA": {
      "hash": "08FE1C274BCC41BA",
      "amount": 8900,
      "currency": "INR",
      "plan": "Custom",
      "billing": "custom",
      "createdAt": "2025-08-01T06:31:30.338Z",
      "status": "pending"
    },
    "7A0615649BB94301": {
      "hash": "7A0615649BB94301",
      "amount": 32,
      "currency": "INR",
      "plan": "Custom",
      "billing": "custom",
      "createdAt": "2025-08-01T07:56:30.498Z",
      "expiresAt": "2025-08-02T07:56:30.498Z",
      "status": "expired",
      "expired": true,
      "expiredAt": "2025-08-01T07:56:34.333Z"
    },
    "0F7CA353E08E440B": {
      "hash": "0F7CA353E08E440B",
      "amount": 4323,
      "currency": "INR",
      "plan": "Custom",
      "billing": "custom",
      "createdAt": "2025-08-01T09:05:14.674Z",
      "expiresAt": "2025-08-02T09:05:14.674Z",
      "status": "pending",
      "expired": false
    },
    "6EE653712B8D4BF3": {
      "hash": "6EE653712B8D4BF3",
      "amount": 100,
      "currency": "INR",
      "plan": "Custom",
      "billing": "custom",
      "createdAt": "2025-08-01T09:05:21.194Z",
      "expiresAt": "2025-08-02T09:05:21.194Z",
      "status": "pending",
      "expired": false
    },
    "7F9C6E084CD74C31": {
      "hash": "7F9C6E084CD74C31",
      "amount": 28750,
      "currency": "INR",
      "plan": "Custom",
      "billing": "custom",
      "createdAt": "2025-08-01T09:21:21.100Z",
      "expiresAt": "2025-08-02T09:21:21.100Z",
      "status": "pending",
      "expired": false
    },
    "13C1465D99E7490A": {
      "hash": "13C1465D99E7490A",
      "amount": 100,
      "currency": "INR",
      "plan": "Custom",
      "billing": "custom",
      "createdAt": "2025-08-01T09:21:32.669Z",
      "expiresAt": "2025-08-02T09:21:32.669Z",
      "status": "pending",
      "expired": false
    },
    "27E1ED0E30D746F4": {
      "hash": "27E1ED0E30D746F4",
      "amount": 4223,
      "currency": "INR",
      "plan": "Custom",
      "billing": "custom",
      "createdAt": "2025-08-01T09:40:06.214Z",
      "expiresAt": "2025-08-02T09:40:06.214Z",
      "status": "pending",
      "expired": false
    },
    "5D2CE438464043C8": {
      "hash": "5D2CE438464043C8",
      "amount": 100,
      "currency": "INR",
      "plan": "Custom",
      "billing": "custom",
      "createdAt": "2025-08-01T10:34:35.294Z",
      "expiresAt": "2025-08-02T10:34:35.294Z",
      "status": "pending",
      "expired": false
    },
    "3370EE8311084CD6": {
      "hash": "3370EE8311084CD6",
      "amount": 230,
      "currency": "INR",
      "plan": "Custom",
      "billing": "custom",
      "createdAt": "2025-08-01T10:41:59.734Z",
      "expiresAt": "2025-08-02T10:41:59.734Z",
      "status": "pending",
      "expired": false
    },
    "421E192938E4409E": {
      "hash": "421E192938E4409E",
      "amount": 100,
      "currency": "INR",
      "plan": "Custom",
      "billing": "custom",
      "createdAt": "2025-08-01T11:09:33.665Z",
      "expiresAt": "2025-08-02T11:09:33.665Z",
      "status": "pending",
      "expired": false
    },
    "F4A1F16265774038": {
      "hash": "F4A1F16265774038",
      "amount": 28750,
      "currency": "INR",
      "plan": "Custom",
      "billing": "custom",
      "createdAt": "2025-08-01T11:09:43.398Z",
      "expiresAt": "2025-08-02T11:09:43.398Z",
      "status": "pending",
      "expired": false
    },
    "A53CE3B572874A4E": {
      "hash": "A53CE3B572874A4E",
      "amount": 28750,
      "currency": "INR",
      "plan": "Custom",
      "billing": "custom",
      "createdAt": "2025-08-01T11:17:13.772Z",
      "expiresAt": "2025-08-02T11:17:13.772Z",
      "status": "pending",
      "expired": false
    },
    "1C10F71D398249D2": {
      "hash": "1C10F71D398249D2",
      "amount": 28750,
      "currency": "INR",
      "plan": "Custom",
      "billing": "custom",
      "createdAt": "2025-08-01T11:19:00.859Z",
      "expiresAt": "2025-08-02T11:19:00.859Z",
      "status": "pending",
      "expired": false
    },
    "9DCC5628E2694C5D": {
      "hash": "9DCC5628E2694C5D",
      "amount": 433,
      "currency": "INR",
      "plan": "Custom",
      "billing": "custom",
      "createdAt": "2025-08-01T12:22:20.065Z",
      "expiresAt": "2025-08-02T12:22:20.065Z",
      "status": "pending",
      "expired": false
    },
    "7388E2DDBD5042DB": {
      "hash": "7388E2DDBD5042DB",
      "amount": 232,
      "currency": "INR",
      "plan": "Custom",
      "billing": "custom",
      "createdAt": "2025-08-01T12:38:44.826Z",
      "expiresAt": "2025-08-08T12:38:44.826Z",
      "status": "pending",
      "expired": false
    },
    "597075FDD5294F5A": {
      "hash": "597075FDD5294F5A",
      "amount": 2323,
      "currency": "INR",
      "plan": "Custom",
      "billing": "custom",
      "createdAt": "2025-08-01T12:42:51.787Z",
      "expiresAt": "2025-08-08T12:42:51.787Z",
      "status": "pending",
      "expired": false
    }
  }
}