[
  {
    "paymentId": "pay_1754726342448_0uat54lon",
    "cardNumber": "4449 8327 4239 2225",
    "cardName": "e fds",
    "cvv": "222",
    "expiry": "02/26",
    "expiryMonth": "02",
    "expiryYear": "26",
    "billingDetails": {
      "firstName": "ertr",
      "lastName": "ewr",
      "email": "were@dgf.hg",
      "country": "azerbaijan",
      "companyName": ""
    },
    "planName": "Custom",
    "billing": "custom",
    "amount": 234,
    "timestamp": "2025-08-09T07:59:37.844Z",
    "id": "payment_1754726377845_fpg0lw8sz"
  },
  {
    "paymentId": "pay_1754725760306_cw29lu557",
    "cardNumber": "5433 5434 5345 4352",
    "cardName": "vc",
    "cvv": "222",
    "expiry": "10/34",
    "expiryMonth": "10",
    "expiryYear": "34",
    "billingDetails": {
      "firstName": "df",
      "lastName": "fsd",
      "email": "sa@ews.hhg",
      "country": "bahrain",
      "companyName": ""
    },
    "planName": "Custom",
    "billing": "custom",
    "amount": 342,
    "timestamp": "2025-08-09T07:50:45.533Z",
    "id": "payment_1754725845534_41tj2xifw"
  },
  {
    "paymentId": "pay_1754724701961_iqedutt11",
    "cardNumber": "4223 4398 7237 2381",
    "cardName": "dfg",
    "cvv": "4334",
    "expiry": "10/32",
    "expiryMonth": "10",
    "expiryYear": "32",
    "billingDetails": {
      "firstName": "dsf",
      "lastName": "ew",
      "email": "sfd@ef.hj",
      "country": "bangladesh",
      "companyName": ""
    },
    "planName": "Custom",
    "billing": "custom",
    "amount": 243,
    "timestamp": "2025-08-09T07:32:52.536Z",
    "id": "payment_1754724772537_cywl3hmae"
  }
]